<?xml version="1.0" encoding="utf-8"?>
<Model xmlns:xsi="http://www.w3.org/2001/XMLSchema-instance" xmlns:xsd="http://www.w3.org/2001/XMLSchema">
	<Name>Axe_2H_War_B_01</Name>
	<Bones>
		<Bone>
			<Billboard>0</Billboard>
			<Parent>-1</Parent>
			<Translation x="0" y="0" z="0" />
			<Rotation x="0" y="0" z="-0" w="1" />
			<Scale x="1" y="1" z="1" />
			<Position x="-0.165624" y="-0.02267102" z="0.006548556" />
		</Bone>
		<Bone>
			<Billboard>512</Billboard>
			<Parent>-1</Parent>
			<Translation x="0" y="0" z="0" />
			<Rotation x="0" y="0" z="-0" w="1" />
			<Scale x="1.8" y="1.8" z="1.8" />
			<Position x="0.6258474" y="-0.2387621" z="0.004303324" />
		</Bone>
		<Bone>
			<Billboard>512</Billboard>
			<Parent>-1</Parent>
			<Translation x="0" y="0" z="0" />
			<Rotation x="0" y="0" z="-0" w="1" />
			<Scale x="1.8" y="1.8" z="1.8" />
			<Position x="0.8556984" y="-0.04529978" z="0.004303323" />
		</Bone>
		<Bone>
			<Billboard>512</Billboard>
			<Parent>-1</Parent>
			<Translation x="0" y="0" z="0" />
			<Rotation x="0" y="0" z="-0" w="1" />
			<Scale x="1.8" y="1.8" z="1.8" />
			<Position x="0.903035" y="-0.2799639" z="-0" />
		</Bone>
		<Bone>
			<Billboard>0</Billboard>
			<Parent>-1</Parent>
			<Translation x="0" y="0" z="0" />
			<Rotation x="0" y="0" z="-0" w="1" />
			<Scale x="1" y="1" z="1" />
			<Position x="1.018934" y="-0.3468691" z="-0" />
		</Bone>
		<Bone>
			<Billboard>0</Billboard>
			<Parent>-1</Parent>
			<Translation x="0" y="0" z="0" />
			<Rotation x="0" y="0" z="-0" w="1" />
			<Scale x="1" y="1" z="1" />
			<Position x="0.3194148" y="-0.1678131" z="-0" />
		</Bone>
	</Bones>
	<Vertices>
		<Vertex>
			<Position x="0.682043" y="0.05528306" z="0.00665383" />
			<Bones>
				<Bone index="0" weight="255" />
				<Bone index="0" weight="0" />
				<Bone index="0" weight="0" />
				<Bone index="0" weight="0" />
			</Bones>
			<Normal x="-0.9995009" y="-0.001061197" z="0.03157069" />
			<Texture x="0.578125" y="0.015625" />
		</Vertex>
		<Vertex>
			<Position x="0.6798643" y="-0.03578316" z="0.03577323" />
			<Bones>
				<Bone index="0" weight="255" />
				<Bone index="0" weight="0" />
				<Bone index="0" weight="0" />
				<Bone index="0" weight="0" />
			</Bones>
			<Normal x="-0.9991347" y="-0.005846903" z="0.04117939" />
			<Texture x="0.5379957" y="0.2625108" />
		</Vertex>
		<Vertex>
			<Position x="0.6820429" y="0.004349198" z="0.05289948" />
			<Bones>
				<Bone index="0" weight="255" />
				<Bone index="0" weight="0" />
				<Bone index="0" weight="0" />
				<Bone index="0" weight="0" />
			</Bones>
			<Normal x="-0.9984944" y="-0.04060929" z="0.03687469" />
			<Texture x="0.515625" y="0.15625" />
		</Vertex>
		<Vertex>
			<Position x="0.9694669" y="-0.04411644" z="-0.02342428" />
			<Bones>
				<Bone index="0" weight="255" />
				<Bone index="0" weight="0" />
				<Bone index="0" weight="0" />
				<Bone index="0" weight="0" />
			</Bones>
			<Normal x="0.976762" y="-6.511574E-06" z="0.2143268" />
			<Texture x="0.9371747" y="0.2696279" />
		</Vertex>
		<Vertex>
			<Position x="0.9693031" y="-0.04337212" z="0.03749034" />
			<Bones>
				<Bone index="0" weight="255" />
				<Bone index="0" weight="0" />
				<Bone index="0" weight="0" />
				<Bone index="0" weight="0" />
			</Bones>
			<Normal x="0.9767621" y="-7.183336E-06" z="0.2143263" />
			<Texture x="0.9911343" y="0.2678946" />
		</Vertex>
		<Vertex>
			<Position x="1.036806" y="-0.3510046" z="0.006532529" />
			<Bones>
				<Bone index="0" weight="255" />
				<Bone index="0" weight="0" />
				<Bone index="0" weight="0" />
				<Bone index="0" weight="0" />
			</Bones>
			<Normal x="0.9767618" y="-7.162766E-06" z="0.2143279" />
			<Texture x="0.984375" y="0.984375" />
		</Vertex>
		<Vertex>
			<Position x="0.9587846" y="0.004564284" z="0.0534365" />
			<Bones>
				<Bone index="0" weight="255" />
				<Bone index="0" weight="0" />
				<Bone index="0" weight="0" />
				<Bone index="0" weight="0" />
			</Bones>
			<Normal x="0.9896321" y="-5.982287E-06" z="0.1436255" />
			<Texture x="0.9921875" y="0.15625" />
		</Vertex>
		<Vertex>
			<Position x="0.9587852" y="0.004564202" z="-0.03961175" />
			<Bones>
				<Bone index="0" weight="255" />
				<Bone index="0" weight="0" />
				<Bone index="0" weight="0" />
				<Bone index="0" weight="0" />
			</Bones>
			<Normal x="0.9941738" y="-5.356226E-06" z="0.1077885" />
			<Texture x="0.9296875" y="0.15625" />
		</Vertex>
		<Vertex>
			<Position x="0.9587852" y="0.05489667" z="0.006658439" />
			<Bones>
				<Bone index="0" weight="255" />
				<Bone index="0" weight="0" />
				<Bone index="0" weight="0" />
				<Bone index="0" weight="0" />
			</Bones>
			<Normal x="1" y="-5.481983E-06" z="-6.855557E-06" />
			<Texture x="0.9296875" y="0.015625" />
		</Vertex>
		<Vertex>
			<Position x="0.9694669" y="-0.04411644" z="-0.02342428" />
			<Bones>
				<Bone index="0" weight="255" />
				<Bone index="0" weight="0" />
				<Bone index="0" weight="0" />
				<Bone index="0" weight="0" />
			</Bones>
			<Normal x="0.0824827" y="0.881247" z="-0.4654034" />
			<Texture x="0.9371747" y="0.2696279" />
		</Vertex>
		<Vertex>
			<Position x="0.8190088" y="-0.04596274" z="-0.02219553" />
			<Bones>
				<Bone index="0" weight="255" />
				<Bone index="0" weight="0" />
				<Bone index="0" weight="0" />
				<Bone index="0" weight="0" />
			</Bones>
			<Normal x="-0.00944014" y="0.776343" z="-0.6302399" />
			<Texture x="0.765625" y="0.28125" />
		</Vertex>
		<Vertex>
			<Position x="0.8190091" y="0.004572548" z="-0.06322041" />
			<Bones>
				<Bone index="0" weight="255" />
				<Bone index="0" weight="0" />
				<Bone index="0" weight="0" />
				<Bone index="0" weight="0" />
			</Bones>
			<Normal x="-0.003274832" y="0.9928545" z="-0.1192859" />
			<Texture x="0.765625" y="0.15625" />
		</Vertex>
		<Vertex>
			<Position x="0.9587852" y="0.004564202" z="-0.03961175" />
			<Bones>
				<Bone index="0" weight="255" />
				<Bone index="0" weight="0" />
				<Bone index="0" weight="0" />
				<Bone index="0" weight="0" />
			</Bones>
			<Normal x="0.1582903" y="0.9059655" z="0.3926458" />
			<Texture x="0.9296875" y="0.15625" />
		</Vertex>
		<Vertex>
			<Position x="0.8190091" y="0.08354339" z="0.006692082" />
			<Bones>
				<Bone index="0" weight="255" />
				<Bone index="0" weight="0" />
				<Bone index="0" weight="0" />
				<Bone index="0" weight="0" />
			</Bones>
			<Normal x="-0.0005753699" y="0.7428962" z="0.6694064" />
			<Texture x="0.765625" y="0.015625" />
		</Vertex>
		<Vertex>
			<Position x="0.9587852" y="0.05489667" z="0.006658439" />
			<Bones>
				<Bone index="0" weight="255" />
				<Bone index="0" weight="0" />
				<Bone index="0" weight="0" />
				<Bone index="0" weight="0" />
			</Bones>
			<Normal x="0.1372153" y="0.7292279" z="0.670372" />
			<Texture x="0.9296875" y="0.015625" />
		</Vertex>
		<Vertex>
			<Position x="0.6796992" y="-0.04343249" z="-0.02061118" />
			<Bones>
				<Bone index="0" weight="255" />
				<Bone index="0" weight="0" />
				<Bone index="0" weight="0" />
				<Bone index="0" weight="0" />
			</Bones>
			<Normal x="-0.08907571" y="0.8590835" z="-0.5040248" />
			<Texture x="0.578125" y="0.2820395" />
		</Vertex>
		<Vertex>
			<Position x="0.682043" y="0.00434916" z="-0.0399499" />
			<Bones>
				<Bone index="0" weight="255" />
				<Bone index="0" weight="0" />
				<Bone index="0" weight="0" />
				<Bone index="0" weight="0" />
			</Bones>
			<Normal x="-0.1609604" y="0.9156621" z="0.3683133" />
			<Texture x="0.578125" y="0.15625" />
		</Vertex>
		<Vertex>
			<Position x="0.682043" y="0.05528306" z="0.00665383" />
			<Bones>
				<Bone index="0" weight="255" />
				<Bone index="0" weight="0" />
				<Bone index="0" weight="0" />
				<Bone index="0" weight="0" />
			</Bones>
			<Normal x="-0.1377516" y="0.730739" z="0.6686143" />
			<Texture x="0.578125" y="0.015625" />
		</Vertex>
		<Vertex>
			<Position x="0.8190091" y="0.004572563" z="0.07622317" />
			<Bones>
				<Bone index="0" weight="255" />
				<Bone index="0" weight="0" />
				<Bone index="0" weight="0" />
				<Bone index="0" weight="0" />
			</Bones>
			<Normal x="-0.01019392" y="-0.9925129" z="-0.1217137" />
			<Texture x="0.765625" y="0.15625" />
		</Vertex>
		<Vertex>
			<Position x="0.9693031" y="-0.04337212" z="0.03749034" />
			<Bones>
				<Bone index="0" weight="255" />
				<Bone index="0" weight="0" />
				<Bone index="0" weight="0" />
				<Bone index="0" weight="0" />
			</Bones>
			<Normal x="0.07955885" y="-0.8824964" z="-0.4635412" />
			<Texture x="0.9370603" y="0.2678946" />
		</Vertex>
		<Vertex>
			<Position x="0.9587846" y="0.004564284" z="0.0534365" />
			<Bones>
				<Bone index="0" weight="255" />
				<Bone index="0" weight="0" />
				<Bone index="0" weight="0" />
				<Bone index="0" weight="0" />
			</Bones>
			<Normal x="0.1552774" y="-0.9062435" z="0.3932068" />
			<Texture x="0.9296875" y="0.15625" />
		</Vertex>
		<Vertex>
			<Position x="0.8190088" y="-0.0436477" z="0.03752037" />
			<Bones>
				<Bone index="0" weight="255" />
				<Bone index="0" weight="0" />
				<Bone index="0" weight="0" />
				<Bone index="0" weight="0" />
			</Bones>
			<Normal x="-0.02191662" y="-0.779682" z="-0.625792" />
			<Texture x="0.765625" y="0.28125" />
		</Vertex>
		<Vertex>
			<Position x="0.6798643" y="-0.03578316" z="0.03577323" />
			<Bones>
				<Bone index="0" weight="255" />
				<Bone index="0" weight="0" />
				<Bone index="0" weight="0" />
				<Bone index="0" weight="0" />
			</Bones>
			<Normal x="-0.1010128" y="-0.8549954" z="-0.5087035" />
			<Texture x="0.578125" y="0.2625108" />
		</Vertex>
		<Vertex>
			<Position x="0.6820429" y="0.004349198" z="0.05289948" />
			<Bones>
				<Bone index="0" weight="255" />
				<Bone index="0" weight="0" />
				<Bone index="0" weight="0" />
				<Bone index="0" weight="0" />
			</Bones>
			<Normal x="-0.1614317" y="-0.9182992" z="0.361478" />
			<Texture x="0.578125" y="0.15625" />
		</Vertex>
		<Vertex>
			<Position x="0.8190091" y="0.08354339" z="0.006692082" />
			<Bones>
				<Bone index="0" weight="255" />
				<Bone index="0" weight="0" />
				<Bone index="0" weight="0" />
				<Bone index="0" weight="0" />
			</Bones>
			<Normal x="-0.001404712" y="-0.7435376" z="0.6686926" />
			<Texture x="0.765625" y="0.015625" />
		</Vertex>
		<Vertex>
			<Position x="0.682043" y="0.05528306" z="0.00665383" />
			<Bones>
				<Bone index="0" weight="255" />
				<Bone index="0" weight="0" />
				<Bone index="0" weight="0" />
				<Bone index="0" weight="0" />
			</Bones>
			<Normal x="-0.1375839" y="-0.7333179" z="0.6658195" />
			<Texture x="0.578125" y="0.015625" />
		</Vertex>
		<Vertex>
			<Position x="0.9587852" y="0.05489667" z="0.006658439" />
			<Bones>
				<Bone index="0" weight="255" />
				<Bone index="0" weight="0" />
				<Bone index="0" weight="0" />
				<Bone index="0" weight="0" />
			</Bones>
			<Normal x="0.1383545" y="-0.7254535" z="0.674222" />
			<Texture x="0.9296875" y="0.015625" />
		</Vertex>
		<Vertex>
			<Position x="0.6796992" y="-0.04343249" z="-0.02061118" />
			<Bones>
				<Bone index="0" weight="255" />
				<Bone index="0" weight="0" />
				<Bone index="0" weight="0" />
				<Bone index="0" weight="0" />
			</Bones>
			<Normal x="-0.0129263" y="0.9960353" z="-0.08801418" />
			<Texture x="0.578125" y="0.2820395" />
		</Vertex>
		<Vertex>
			<Position x="0.8190088" y="-0.04596274" z="-0.02219553" />
			<Bones>
				<Bone index="0" weight="255" />
				<Bone index="0" weight="0" />
				<Bone index="0" weight="0" />
				<Bone index="0" weight="0" />
			</Bones>
			<Normal x="-0.006114571" y="0.9958013" z="-0.09133685" />
			<Texture x="0.765625" y="0.28125" />
		</Vertex>
		<Vertex>
			<Position x="0.6765115" y="-0.10842" z="-0.01482722" />
			<Bones>
				<Bone index="0" weight="255" />
				<Bone index="0" weight="0" />
				<Bone index="0" weight="0" />
				<Bone index="0" weight="0" />
			</Bones>
			<Normal x="-0.04119475" y="0.9965554" z="-0.0719742" />
			<Texture x="0.578125" y="0.453125" />
		</Vertex>
		<Vertex>
			<Position x="0.5301484" y="-0.3099826" z="0.006532494" />
			<Bones>
				<Bone index="0" weight="255" />
				<Bone index="0" weight="0" />
				<Bone index="0" weight="0" />
				<Bone index="0" weight="0" />
			</Bones>
			<Normal x="-0.05551668" y="0.9972184" z="-0.0497322" />
			<Texture x="0.640625" y="0.984375" />
		</Vertex>
		<Vertex>
			<Position x="0.2954203" y="-0.1520816" z="0.006532477" />
			<Bones>
				<Bone index="0" weight="255" />
				<Bone index="0" weight="0" />
				<Bone index="0" weight="0" />
				<Bone index="0" weight="0" />
			</Bones>
			<Normal x="-0.0266805" y="0.9988569" z="-0.03966208" />
			<Texture x="0.5078125" y="0.984375" />
		</Vertex>
		<Vertex>
			<Position x="0.5652494" y="-0.165502" z="-0.0001420516" />
			<Bones>
				<Bone index="0" weight="255" />
				<Bone index="0" weight="0" />
				<Bone index="0" weight="0" />
				<Bone index="0" weight="0" />
			</Bones>
			<Normal x="-0.07480891" y="0.9968082" z="-0.02787483" />
			<Texture x="0.5703125" y="0.671875" />
		</Vertex>
		<Vertex>
			<Position x="0.8456029" y="-0.3669348" z="0.006532515" />
			<Bones>
				<Bone index="0" weight="255" />
				<Bone index="0" weight="0" />
				<Bone index="0" weight="0" />
				<Bone index="0" weight="0" />
			</Bones>
			<Normal x="-0.007151443" y="0.9958572" z="-0.09064867" />
			<Texture x="0.78125" y="0.984375" />
		</Vertex>
		<Vertex>
			<Position x="1.036806" y="-0.3510046" z="0.006532529" />
			<Bones>
				<Bone index="0" weight="255" />
				<Bone index="0" weight="0" />
				<Bone index="0" weight="0" />
				<Bone index="0" weight="0" />
			</Bones>
			<Normal x="0.0002302797" y="0.9956099" z="-0.09359949" />
			<Texture x="0.984375" y="0.984375" />
		</Vertex>
		<Vertex>
			<Position x="0.9694669" y="-0.04411644" z="-0.02342428" />
			<Bones>
				<Bone index="0" weight="255" />
				<Bone index="0" weight="0" />
				<Bone index="0" weight="0" />
				<Bone index="0" weight="0" />
			</Bones>
			<Normal x="-0.006916121" y="0.9950978" z="-0.09865373" />
			<Texture x="0.9371747" y="0.2696279" />
		</Vertex>
		<Vertex>
			<Position x="0.6798643" y="-0.03578316" z="0.03577323" />
			<Bones>
				<Bone index="0" weight="255" />
				<Bone index="0" weight="0" />
				<Bone index="0" weight="0" />
				<Bone index="0" weight="0" />
			</Bones>
			<Normal x="-0.01719804" y="-0.9964076" z="-0.08292253" />
			<Texture x="0.578125" y="0.2625108" />
		</Vertex>
		<Vertex>
			<Position x="0.6759564" y="-0.107774" z="0.02971459" />
			<Bones>
				<Bone index="0" weight="255" />
				<Bone index="0" weight="0" />
				<Bone index="0" weight="0" />
				<Bone index="0" weight="0" />
			</Bones>
			<Normal x="-0.04672606" y="-0.9962122" z="-0.07333476" />
			<Texture x="0.578125" y="0.453125" />
		</Vertex>
		<Vertex>
			<Position x="0.8190088" y="-0.0436477" z="0.03752037" />
			<Bones>
				<Bone index="0" weight="255" />
				<Bone index="0" weight="0" />
				<Bone index="0" weight="0" />
				<Bone index="0" weight="0" />
			</Bones>
			<Normal x="-0.005013613" y="-0.9956049" z="-0.09351917" />
			<Texture x="0.765625" y="0.28125" />
		</Vertex>
		<Vertex>
			<Position x="0.2954203" y="-0.1520816" z="0.006532477" />
			<Bones>
				<Bone index="0" weight="255" />
				<Bone index="0" weight="0" />
				<Bone index="0" weight="0" />
				<Bone index="0" weight="0" />
			</Bones>
			<Normal x="-0.02714491" y="-0.9988167" z="-0.0403522" />
			<Texture x="0.5078125" y="0.984375" />
		</Vertex>
		<Vertex>
			<Position x="0.5301484" y="-0.3099826" z="0.006532494" />
			<Bones>
				<Bone index="0" weight="255" />
				<Bone index="0" weight="0" />
				<Bone index="0" weight="0" />
				<Bone index="0" weight="0" />
			</Bones>
			<Normal x="-0.06191328" y="-0.9967574" z="-0.05139353" />
			<Texture x="0.640625" y="0.984375" />
		</Vertex>
		<Vertex>
			<Position x="0.565288" y="-0.1650835" z="0.01334142" />
			<Bones>
				<Bone index="0" weight="255" />
				<Bone index="0" weight="0" />
				<Bone index="0" weight="0" />
				<Bone index="0" weight="0" />
			</Bones>
			<Normal x="-0.08369688" y="-0.9961385" z="-0.02651188" />
			<Texture x="0.5703125" y="0.671875" />
		</Vertex>
		<Vertex>
			<Position x="0.8456029" y="-0.3669348" z="0.006532515" />
			<Bones>
				<Bone index="0" weight="255" />
				<Bone index="0" weight="0" />
				<Bone index="0" weight="0" />
				<Bone index="0" weight="0" />
			</Bones>
			<Normal x="-0.007151975" y="-0.9952259" z="-0.09733591" />
			<Texture x="0.78125" y="0.984375" />
		</Vertex>
		<Vertex>
			<Position x="1.036806" y="-0.3510046" z="0.006532529" />
			<Bones>
				<Bone index="0" weight="255" />
				<Bone index="0" weight="0" />
				<Bone index="0" weight="0" />
				<Bone index="0" weight="0" />
			</Bones>
			<Normal x="0.004138939" y="-0.995236" z="-0.09740707" />
			<Texture x="0.984375" y="0.984375" />
		</Vertex>
		<Vertex>
			<Position x="0.9693031" y="-0.04337212" z="0.03749034" />
			<Bones>
				<Bone index="0" weight="255" />
				<Bone index="0" weight="0" />
				<Bone index="0" weight="0" />
				<Bone index="0" weight="0" />
			</Bones>
			<Normal x="0.0003822036" y="-0.994983" z="-0.1000436" />
			<Texture x="0.9370603" y="0.2678946" />
		</Vertex>
		<Vertex>
			<Position x="-0.2599245" y="-0.03093667" z="0.006661736" />
			<Bones>
				<Bone index="0" weight="255" />
				<Bone index="0" weight="0" />
				<Bone index="0" weight="0" />
				<Bone index="0" weight="0" />
			</Bones>
			<Normal x="0.1253759" y="0.2188721" z="-0.9676652" />
			<Texture x="0.0078125" y="0.46875" />
		</Vertex>
		<Vertex>
			<Position x="-0.2599245" y="0.004434097" z="-0.02475179" />
			<Bones>
				<Bone index="0" weight="255" />
				<Bone index="0" weight="0" />
				<Bone index="0" weight="0" />
				<Bone index="0" weight="0" />
			</Bones>
			<Normal x="0.1535933" y="0.9881318" z="-0.002169364" />
			<Texture x="0.0078125" y="0.25" />
		</Vertex>
		<Vertex>
			<Position x="0.192535" y="0.004434101" z="-0.02475176" />
			<Bones>
				<Bone index="0" weight="255" />
				<Bone index="0" weight="0" />
				<Bone index="0" weight="0" />
				<Bone index="0" weight="0" />
			</Bones>
			<Normal x="6.878345E-08" y="1" z="-1.604051E-07" />
			<Texture x="0.4921875" y="0.25" />
		</Vertex>
		<Vertex>
			<Position x="0.1923881" y="-0.03093667" z="0.006661756" />
			<Bones>
				<Bone index="0" weight="255" />
				<Bone index="0" weight="0" />
				<Bone index="0" weight="0" />
				<Bone index="0" weight="0" />
			</Bones>
			<Normal x="2.769061E-10" y="-0.001794331" z="-0.9999984" />
			<Texture x="0.4921875" y="0.46875" />
		</Vertex>
		<Vertex>
			<Position x="0.192388" y="0.03980488" z="0.006661755" />
			<Bones>
				<Bone index="0" weight="255" />
				<Bone index="0" weight="0" />
				<Bone index="0" weight="0" />
				<Bone index="0" weight="0" />
			</Bones>
			<Normal x="-9.970568E-09" y="-0.001794333" z="0.9999984" />
			<Texture x="0.4921875" y="0.015625" />
		</Vertex>
		<Vertex>
			<Position x="-0.2599245" y="0.03980487" z="0.006661736" />
			<Bones>
				<Bone index="0" weight="255" />
				<Bone index="0" weight="0" />
				<Bone index="0" weight="0" />
				<Bone index="0" weight="0" />
			</Bones>
			<Normal x="0.188504" y="-0.1577948" z="0.9693127" />
			<Texture x="0.0078125" y="0.015625" />
		</Vertex>
		<Vertex>
			<Position x="0.192547" y="0.0044341" z="0.03784894" />
			<Bones>
				<Bone index="0" weight="255" />
				<Bone index="0" weight="0" />
				<Bone index="0" weight="0" />
				<Bone index="0" weight="0" />
			</Bones>
			<Normal x="-7.294885E-08" y="-1" z="-1.711628E-07" />
			<Texture x="0.4921875" y="0.25" />
		</Vertex>
		<Vertex>
			<Position x="-0.2599245" y="0.004434095" z="0.03784891" />
			<Bones>
				<Bone index="0" weight="255" />
				<Bone index="0" weight="0" />
				<Bone index="0" weight="0" />
				<Bone index="0" weight="0" />
			</Bones>
			<Normal x="0.1467687" y="-0.9469786" z="-0.2858157" />
			<Texture x="0.0078125" y="0.25" />
		</Vertex>
		<Vertex>
			<Position x="0.192388" y="0.03980488" z="0.006661755" />
			<Bones>
				<Bone index="0" weight="255" />
				<Bone index="0" weight="0" />
				<Bone index="0" weight="0" />
				<Bone index="0" weight="0" />
			</Bones>
			<Normal x="-9.970568E-09" y="-0.001794333" z="0.9999984" />
			<Texture x="0.1015625" y="0.515625" />
		</Vertex>
		<Vertex>
			<Position x="0.192547" y="0.0044341" z="0.03784894" />
			<Bones>
				<Bone index="0" weight="255" />
				<Bone index="0" weight="0" />
				<Bone index="0" weight="0" />
				<Bone index="0" weight="0" />
			</Bones>
			<Normal x="-7.294885E-08" y="-1" z="-1.711628E-07" />
			<Texture x="0.1015625" y="0.75" />
		</Vertex>
		<Vertex>
			<Position x="0.6547217" y="0.004434091" z="0.03784897" />
			<Bones>
				<Bone index="0" weight="255" />
				<Bone index="0" weight="0" />
				<Bone index="0" weight="0" />
				<Bone index="0" weight="0" />
			</Bones>
			<Normal x="-7.970822E-09" y="-1" z="-1.976512E-07" />
			<Texture x="0.4921875" y="0.75" />
		</Vertex>
		<Vertex>
			<Position x="0.6546422" y="0.03980488" z="0.006661776" />
			<Bones>
				<Bone index="0" weight="255" />
				<Bone index="0" weight="0" />
				<Bone index="0" weight="0" />
				<Bone index="0" weight="0" />
			</Bones>
			<Normal x="-1.828579E-07" y="-0.001794183" z="0.9999984" />
			<Texture x="0.4921875" y="0.515625" />
		</Vertex>
		<Vertex>
			<Position x="0.192535" y="0.004434101" z="-0.02475176" />
			<Bones>
				<Bone index="0" weight="255" />
				<Bone index="0" weight="0" />
				<Bone index="0" weight="0" />
				<Bone index="0" weight="0" />
			</Bones>
			<Normal x="6.878345E-08" y="1" z="-1.604051E-07" />
			<Texture x="0.1015625" y="0.75" />
		</Vertex>
		<Vertex>
			<Position x="0.6547157" y="0.004434092" z="-0.02475173" />
			<Bones>
				<Bone index="0" weight="255" />
				<Bone index="0" weight="0" />
				<Bone index="0" weight="0" />
				<Bone index="0" weight="0" />
			</Bones>
			<Normal x="6.147764E-09" y="1" z="-1.869777E-07" />
			<Texture x="0.4921875" y="0.75" />
		</Vertex>
		<Vertex>
			<Position x="0.1923881" y="-0.03093667" z="0.006661756" />
			<Bones>
				<Bone index="0" weight="255" />
				<Bone index="0" weight="0" />
				<Bone index="0" weight="0" />
				<Bone index="0" weight="0" />
			</Bones>
			<Normal x="2.769061E-10" y="-0.001794331" z="-0.9999984" />
			<Texture x="0.1015625" y="0.984375" />
		</Vertex>
		<Vertex>
			<Position x="0.6546422" y="-0.03093667" z="0.006661777" />
			<Bones>
				<Bone index="0" weight="255" />
				<Bone index="0" weight="0" />
				<Bone index="0" weight="0" />
				<Bone index="0" weight="0" />
			</Bones>
			<Normal x="1.797066E-07" y="-0.001794166" z="-0.9999984" />
			<Texture x="0.4921875" y="0.984375" />
		</Vertex>
		<Vertex>
			<Position x="0.6546422" y="0.03980488" z="0.006661776" />
			<Bones>
				<Bone index="0" weight="255" />
				<Bone index="0" weight="0" />
				<Bone index="0" weight="0" />
				<Bone index="0" weight="0" />
			</Bones>
			<Normal x="-1.828579E-07" y="-0.001794183" z="0.9999984" />
			<Texture x="0.1015625" y="0.515625" />
		</Vertex>
		<Vertex>
			<Position x="0.6547217" y="0.004434091" z="0.03784897" />
			<Bones>
				<Bone index="0" weight="255" />
				<Bone index="0" weight="0" />
				<Bone index="0" weight="0" />
				<Bone index="0" weight="0" />
			</Bones>
			<Normal x="-7.970822E-09" y="-1" z="-1.976512E-07" />
			<Texture x="0.1015625" y="0.75" />
		</Vertex>
		<Vertex>
			<Position x="0.989132" y="0.004434211" z="0.03784898" />
			<Bones>
				<Bone index="0" weight="255" />
				<Bone index="0" weight="0" />
				<Bone index="0" weight="0" />
				<Bone index="0" weight="0" />
			</Bones>
			<Normal x="0.3922053" y="-0.8825497" z="0.2593859" />
			<Texture x="0.4921875" y="0.75" />
		</Vertex>
		<Vertex>
			<Position x="0.9891322" y="0.039805" z="0.006661789" />
			<Bones>
				<Bone index="0" weight="255" />
				<Bone index="0" weight="0" />
				<Bone index="0" weight="0" />
				<Bone index="0" weight="0" />
			</Bones>
			<Normal x="0.6854567" y="0.2554392" z="0.6818357" />
			<Texture x="0.4921875" y="0.515625" />
		</Vertex>
		<Vertex>
			<Position x="0.989132" y="-0.03093655" z="0.006661789" />
			<Bones>
				<Bone index="0" weight="255" />
				<Bone index="0" weight="0" />
				<Bone index="0" weight="0" />
				<Bone index="0" weight="0" />
			</Bones>
			<Normal x="0.6854543" y="-0.2578875" z="-0.6809158" />
			<Texture x="0.4140625" y="0.9375" />
		</Vertex>
		<Vertex>
			<Position x="0.9891322" y="0.004434213" z="-0.02475171" />
			<Bones>
				<Bone index="0" weight="255" />
				<Bone index="0" weight="0" />
				<Bone index="0" weight="0" />
				<Bone index="0" weight="0" />
			</Bones>
			<Normal x="0.3930686" y="0.8816848" z="-0.2610153" />
			<Texture x="0.4921875" y="0.75" />
		</Vertex>
		<Vertex>
			<Position x="0.989132" y="-0.03093655" z="0.006661789" />
			<Bones>
				<Bone index="0" weight="255" />
				<Bone index="0" weight="0" />
				<Bone index="0" weight="0" />
				<Bone index="0" weight="0" />
			</Bones>
			<Normal x="0.6854543" y="-0.2578875" z="-0.6809158" />
			<Texture x="0.4921875" y="0.984375" />
		</Vertex>
		<Vertex>
			<Position x="0.6546422" y="-0.03093667" z="0.006661777" />
			<Bones>
				<Bone index="0" weight="255" />
				<Bone index="0" weight="0" />
				<Bone index="0" weight="0" />
				<Bone index="0" weight="0" />
			</Bones>
			<Normal x="1.797066E-07" y="-0.001794166" z="-0.9999984" />
			<Texture x="0.1015625" y="0.984375" />
		</Vertex>
		<Vertex>
			<Position x="0.6547157" y="0.004434092" z="-0.02475173" />
			<Bones>
				<Bone index="0" weight="255" />
				<Bone index="0" weight="0" />
				<Bone index="0" weight="0" />
				<Bone index="0" weight="0" />
			</Bones>
			<Normal x="6.147764E-09" y="1" z="-1.869777E-07" />
			<Texture x="0.1015625" y="0.75" />
		</Vertex>
		<Vertex>
			<Position x="-0.2599245" y="0.004434097" z="-0.02475179" />
			<Bones>
				<Bone index="0" weight="255" />
				<Bone index="0" weight="0" />
				<Bone index="0" weight="0" />
				<Bone index="0" weight="0" />
			</Bones>
			<Normal x="0.1535933" y="0.9881318" z="-0.002169364" />
			<Texture x="0.1328125" y="0.75" />
		</Vertex>
		<Vertex>
			<Position x="-0.3900118" y="0.004650229" z="-0.06761698" />
			<Bones>
				<Bone index="0" weight="255" />
				<Bone index="0" weight="0" />
				<Bone index="0" weight="0" />
				<Bone index="0" weight="0" />
			</Bones>
			<Normal x="-0.3472638" y="0.9120309" z="0.2181914" />
			<Texture x="0.015625" y="0.75" />
		</Vertex>
		<Vertex>
			<Position x="-0.2599245" y="0.03980487" z="0.006661736" />
			<Bones>
				<Bone index="0" weight="255" />
				<Bone index="0" weight="0" />
				<Bone index="0" weight="0" />
				<Bone index="0" weight="0" />
			</Bones>
			<Normal x="0.188504" y="-0.1577948" z="0.9693127" />
			<Texture x="0.1328125" y="0.515625" />
		</Vertex>
		<Vertex>
			<Position x="-0.3900117" y="-0.0736836" z="0.006687866" />
			<Bones>
				<Bone index="0" weight="255" />
				<Bone index="0" weight="0" />
				<Bone index="0" weight="0" />
				<Bone index="0" weight="0" />
			</Bones>
			<Normal x="-0.2557776" y="-0.001497129" z="-0.9667345" />
			<Texture x="0.015625" y="0.984375" />
		</Vertex>
		<Vertex>
			<Position x="-0.4191634" y="0.004583399" z="0.006664907" />
			<Bones>
				<Bone index="0" weight="255" />
				<Bone index="0" weight="0" />
				<Bone index="0" weight="0" />
				<Bone index="0" weight="0" />
			</Bones>
			<Normal x="-0.9999779" y="-0.0006866004" z="0.006613018" />
			<Texture x="0.0078125" y="0.75" />
		</Vertex>
		<Vertex>
			<Position x="-0.3900119" y="0.004650237" z="0.08065868" />
			<Bones>
				<Bone index="0" weight="255" />
				<Bone index="0" weight="0" />
				<Bone index="0" weight="0" />
				<Bone index="0" weight="0" />
			</Bones>
			<Normal x="-0.3462262" y="-0.912728" z="0.2169216" />
			<Texture x="0.015625" y="0.75" />
		</Vertex>
		<Vertex>
			<Position x="-0.3900119" y="0.07986057" z="0.006687876" />
			<Bones>
				<Bone index="0" weight="255" />
				<Bone index="0" weight="0" />
				<Bone index="0" weight="0" />
				<Bone index="0" weight="0" />
			</Bones>
			<Normal x="-0.5437911" y="-0.001137319" z="0.8392198" />
			<Texture x="0.015625" y="0.515625" />
		</Vertex>
		<Vertex>
			<Position x="-0.2599245" y="-0.03093667" z="0.006661736" />
			<Bones>
				<Bone index="0" weight="255" />
				<Bone index="0" weight="0" />
				<Bone index="0" weight="0" />
				<Bone index="0" weight="0" />
			</Bones>
			<Normal x="0.1253759" y="0.2188721" z="-0.9676652" />
			<Texture x="0.1328125" y="0.984375" />
		</Vertex>
		<Vertex>
			<Position x="-0.2599245" y="0.004434095" z="0.03784891" />
			<Bones>
				<Bone index="0" weight="255" />
				<Bone index="0" weight="0" />
				<Bone index="0" weight="0" />
				<Bone index="0" weight="0" />
			</Bones>
			<Normal x="0.1467687" y="-0.9469786" z="-0.2858157" />
			<Texture x="0.1328125" y="0.75" />
		</Vertex>
		<Vertex>
			<Position x="0.2954203" y="-0.1520816" z="0.006532477" />
			<Bones>
				<Bone index="0" weight="255" />
				<Bone index="0" weight="0" />
				<Bone index="0" weight="0" />
				<Bone index="0" weight="0" />
			</Bones>
			<Normal x="0.04888317" y="0.03112986" z="0.9983193" />
			<Texture x="0.5078125" y="0.984375" />
		</Vertex>
		<Vertex>
			<Position x="0.565288" y="-0.1650835" z="0.01334142" />
			<Bones>
				<Bone index="0" weight="255" />
				<Bone index="0" weight="0" />
				<Bone index="0" weight="0" />
				<Bone index="0" weight="0" />
			</Bones>
			<Normal x="-0.2983259" y="0.02612009" z="0.9541066" />
			<Texture x="0.5703125" y="0.671875" />
		</Vertex>
		<Vertex>
			<Position x="0.5652494" y="-0.165502" z="-0.0001420516" />
			<Bones>
				<Bone index="0" weight="255" />
				<Bone index="0" weight="0" />
				<Bone index="0" weight="0" />
				<Bone index="0" weight="0" />
			</Bones>
			<Normal x="-0.2123845" y="0.0297115" z="0.9767344" />
			<Texture x="0.5234375" y="0.671875" />
		</Vertex>
		<Vertex>
			<Position x="0.6765115" y="-0.10842" z="-0.01482722" />
			<Bones>
				<Bone index="0" weight="255" />
				<Bone index="0" weight="0" />
				<Bone index="0" weight="0" />
				<Bone index="0" weight="0" />
			</Bones>
			<Normal x="-0.8400241" y="0.01780804" z="0.5422567" />
			<Texture x="0.5390625" y="0.453125" />
		</Vertex>
		<Vertex>
			<Position x="0.6759564" y="-0.107774" z="0.02971459" />
			<Bones>
				<Bone index="0" weight="255" />
				<Bone index="0" weight="0" />
				<Bone index="0" weight="0" />
				<Bone index="0" weight="0" />
			</Bones>
			<Normal x="-0.8388581" y="0.01834623" z="0.5440409" />
			<Texture x="0.578125" y="0.453125" />
		</Vertex>
		<Vertex>
			<Position x="0.6796992" y="-0.04343249" z="-0.02061118" />
			<Bones>
				<Bone index="0" weight="255" />
				<Bone index="0" weight="0" />
				<Bone index="0" weight="0" />
				<Bone index="0" weight="0" />
			</Bones>
			<Normal x="-0.999276" y="0.0137043" z="0.03549099" />
			<Texture x="0.5210535" y="0.273035" />
		</Vertex>
		<Vertex>
			<Position x="0.682043" y="0.00434916" z="-0.0399499" />
			<Bones>
				<Bone index="0" weight="255" />
				<Bone index="0" weight="0" />
				<Bone index="0" weight="0" />
				<Bone index="0" weight="0" />
			</Bones>
			<Normal x="-0.9987333" y="0.03712261" z="0.0339669" />
			<Texture x="0.5078125" y="0.140625" />
		</Vertex>
	</Vertices>
	<View>
		<Indices>
			<Index>0</Index>
			<Index>1</Index>
			<Index>2</Index>
			<Index>3</Index>
			<Index>4</Index>
			<Index>5</Index>
			<Index>6</Index>
			<Index>7</Index>
			<Index>8</Index>
			<Index>9</Index>
			<Index>10</Index>
			<Index>11</Index>
			<Index>12</Index>
			<Index>13</Index>
			<Index>14</Index>
			<Index>15</Index>
			<Index>16</Index>
			<Index>17</Index>
			<Index>18</Index>
			<Index>19</Index>
			<Index>20</Index>
			<Index>21</Index>
			<Index>22</Index>
			<Index>23</Index>
			<Index>24</Index>
			<Index>25</Index>
			<Index>26</Index>
			<Index>27</Index>
			<Index>28</Index>
			<Index>29</Index>
			<Index>30</Index>
			<Index>31</Index>
			<Index>32</Index>
			<Index>33</Index>
			<Index>34</Index>
			<Index>35</Index>
			<Index>36</Index>
			<Index>37</Index>
			<Index>38</Index>
			<Index>39</Index>
			<Index>40</Index>
			<Index>41</Index>
			<Index>42</Index>
			<Index>43</Index>
			<Index>44</Index>
			<Index>45</Index>
			<Index>46</Index>
			<Index>47</Index>
			<Index>48</Index>
			<Index>49</Index>
			<Index>50</Index>
			<Index>51</Index>
			<Index>52</Index>
			<Index>53</Index>
			<Index>54</Index>
			<Index>55</Index>
			<Index>56</Index>
			<Index>57</Index>
			<Index>58</Index>
			<Index>59</Index>
			<Index>60</Index>
			<Index>61</Index>
			<Index>62</Index>
			<Index>63</Index>
			<Index>64</Index>
			<Index>65</Index>
			<Index>66</Index>
			<Index>67</Index>
			<Index>68</Index>
			<Index>69</Index>
			<Index>70</Index>
			<Index>71</Index>
			<Index>72</Index>
			<Index>73</Index>
			<Index>74</Index>
			<Index>75</Index>
			<Index>76</Index>
			<Index>77</Index>
			<Index>78</Index>
			<Index>79</Index>
			<Index>80</Index>
			<Index>81</Index>
			<Index>82</Index>
			<Index>83</Index>
			<Index>84</Index>
			<Index>85</Index>
		</Indices>
		<Triangles>
			<Triangle>85</Triangle>
			<Triangle>84</Triangle>
			<Triangle>0</Triangle>
			<Triangle>0</Triangle>
			<Triangle>84</Triangle>
			<Triangle>1</Triangle>
			<Triangle>0</Triangle>
			<Triangle>1</Triangle>
			<Triangle>2</Triangle>
			<Triangle>84</Triangle>
			<Triangle>82</Triangle>
			<Triangle>1</Triangle>
			<Triangle>1</Triangle>
			<Triangle>82</Triangle>
			<Triangle>83</Triangle>
			<Triangle>82</Triangle>
			<Triangle>80</Triangle>
			<Triangle>83</Triangle>
			<Triangle>82</Triangle>
			<Triangle>81</Triangle>
			<Triangle>80</Triangle>
			<Triangle>79</Triangle>
			<Triangle>80</Triangle>
			<Triangle>81</Triangle>
			<Triangle>38</Triangle>
			<Triangle>43</Triangle>
			<Triangle>44</Triangle>
			<Triangle>38</Triangle>
			<Triangle>42</Triangle>
			<Triangle>43</Triangle>
			<Triangle>38</Triangle>
			<Triangle>37</Triangle>
			<Triangle>42</Triangle>
			<Triangle>40</Triangle>
			<Triangle>42</Triangle>
			<Triangle>37</Triangle>
			<Triangle>41</Triangle>
			<Triangle>40</Triangle>
			<Triangle>37</Triangle>
			<Triangle>39</Triangle>
			<Triangle>40</Triangle>
			<Triangle>41</Triangle>
			<Triangle>36</Triangle>
			<Triangle>37</Triangle>
			<Triangle>38</Triangle>
			<Triangle>34</Triangle>
			<Triangle>28</Triangle>
			<Triangle>35</Triangle>
			<Triangle>28</Triangle>
			<Triangle>34</Triangle>
			<Triangle>33</Triangle>
			<Triangle>33</Triangle>
			<Triangle>29</Triangle>
			<Triangle>28</Triangle>
			<Triangle>27</Triangle>
			<Triangle>28</Triangle>
			<Triangle>29</Triangle>
			<Triangle>33</Triangle>
			<Triangle>30</Triangle>
			<Triangle>29</Triangle>
			<Triangle>29</Triangle>
			<Triangle>30</Triangle>
			<Triangle>32</Triangle>
			<Triangle>30</Triangle>
			<Triangle>31</Triangle>
			<Triangle>32</Triangle>
			<Triangle>20</Triangle>
			<Triangle>26</Triangle>
			<Triangle>24</Triangle>
			<Triangle>20</Triangle>
			<Triangle>24</Triangle>
			<Triangle>18</Triangle>
			<Triangle>18</Triangle>
			<Triangle>19</Triangle>
			<Triangle>20</Triangle>
			<Triangle>21</Triangle>
			<Triangle>19</Triangle>
			<Triangle>18</Triangle>
			<Triangle>18</Triangle>
			<Triangle>22</Triangle>
			<Triangle>21</Triangle>
			<Triangle>22</Triangle>
			<Triangle>18</Triangle>
			<Triangle>23</Triangle>
			<Triangle>24</Triangle>
			<Triangle>23</Triangle>
			<Triangle>18</Triangle>
			<Triangle>23</Triangle>
			<Triangle>24</Triangle>
			<Triangle>25</Triangle>
			<Triangle>16</Triangle>
			<Triangle>17</Triangle>
			<Triangle>13</Triangle>
			<Triangle>13</Triangle>
			<Triangle>11</Triangle>
			<Triangle>16</Triangle>
			<Triangle>16</Triangle>
			<Triangle>11</Triangle>
			<Triangle>15</Triangle>
			<Triangle>15</Triangle>
			<Triangle>11</Triangle>
			<Triangle>10</Triangle>
			<Triangle>9</Triangle>
			<Triangle>10</Triangle>
			<Triangle>11</Triangle>
			<Triangle>9</Triangle>
			<Triangle>11</Triangle>
			<Triangle>12</Triangle>
			<Triangle>12</Triangle>
			<Triangle>11</Triangle>
			<Triangle>13</Triangle>
			<Triangle>14</Triangle>
			<Triangle>12</Triangle>
			<Triangle>13</Triangle>
			<Triangle>7</Triangle>
			<Triangle>8</Triangle>
			<Triangle>6</Triangle>
			<Triangle>7</Triangle>
			<Triangle>6</Triangle>
			<Triangle>3</Triangle>
			<Triangle>3</Triangle>
			<Triangle>6</Triangle>
			<Triangle>4</Triangle>
			<Triangle>3</Triangle>
			<Triangle>4</Triangle>
			<Triangle>5</Triangle>
			<Triangle>72</Triangle>
			<Triangle>75</Triangle>
			<Triangle>78</Triangle>
			<Triangle>75</Triangle>
			<Triangle>72</Triangle>
			<Triangle>76</Triangle>
			<Triangle>74</Triangle>
			<Triangle>75</Triangle>
			<Triangle>76</Triangle>
			<Triangle>73</Triangle>
			<Triangle>75</Triangle>
			<Triangle>74</Triangle>
			<Triangle>73</Triangle>
			<Triangle>78</Triangle>
			<Triangle>75</Triangle>
			<Triangle>78</Triangle>
			<Triangle>73</Triangle>
			<Triangle>77</Triangle>
			<Triangle>70</Triangle>
			<Triangle>77</Triangle>
			<Triangle>73</Triangle>
			<Triangle>70</Triangle>
			<Triangle>73</Triangle>
			<Triangle>71</Triangle>
			<Triangle>70</Triangle>
			<Triangle>71</Triangle>
			<Triangle>72</Triangle>
			<Triangle>76</Triangle>
			<Triangle>72</Triangle>
			<Triangle>71</Triangle>
			<Triangle>74</Triangle>
			<Triangle>76</Triangle>
			<Triangle>71</Triangle>
			<Triangle>73</Triangle>
			<Triangle>74</Triangle>
			<Triangle>71</Triangle>
			<Triangle>69</Triangle>
			<Triangle>61</Triangle>
			<Triangle>64</Triangle>
			<Triangle>63</Triangle>
			<Triangle>64</Triangle>
			<Triangle>61</Triangle>
			<Triangle>65</Triangle>
			<Triangle>64</Triangle>
			<Triangle>63</Triangle>
			<Triangle>65</Triangle>
			<Triangle>66</Triangle>
			<Triangle>64</Triangle>
			<Triangle>64</Triangle>
			<Triangle>66</Triangle>
			<Triangle>69</Triangle>
			<Triangle>68</Triangle>
			<Triangle>69</Triangle>
			<Triangle>66</Triangle>
			<Triangle>66</Triangle>
			<Triangle>67</Triangle>
			<Triangle>68</Triangle>
			<Triangle>62</Triangle>
			<Triangle>68</Triangle>
			<Triangle>67</Triangle>
			<Triangle>61</Triangle>
			<Triangle>62</Triangle>
			<Triangle>63</Triangle>
			<Triangle>67</Triangle>
			<Triangle>63</Triangle>
			<Triangle>62</Triangle>
			<Triangle>60</Triangle>
			<Triangle>55</Triangle>
			<Triangle>54</Triangle>
			<Triangle>53</Triangle>
			<Triangle>54</Triangle>
			<Triangle>55</Triangle>
			<Triangle>55</Triangle>
			<Triangle>56</Triangle>
			<Triangle>53</Triangle>
			<Triangle>57</Triangle>
			<Triangle>53</Triangle>
			<Triangle>56</Triangle>
			<Triangle>56</Triangle>
			<Triangle>58</Triangle>
			<Triangle>57</Triangle>
			<Triangle>59</Triangle>
			<Triangle>57</Triangle>
			<Triangle>58</Triangle>
			<Triangle>58</Triangle>
			<Triangle>60</Triangle>
			<Triangle>59</Triangle>
			<Triangle>54</Triangle>
			<Triangle>59</Triangle>
			<Triangle>60</Triangle>
			<Triangle>52</Triangle>
			<Triangle>45</Triangle>
			<Triangle>48</Triangle>
			<Triangle>47</Triangle>
			<Triangle>48</Triangle>
			<Triangle>45</Triangle>
			<Triangle>45</Triangle>
			<Triangle>46</Triangle>
			<Triangle>47</Triangle>
			<Triangle>49</Triangle>
			<Triangle>47</Triangle>
			<Triangle>46</Triangle>
			<Triangle>46</Triangle>
			<Triangle>50</Triangle>
			<Triangle>49</Triangle>
			<Triangle>51</Triangle>
			<Triangle>49</Triangle>
			<Triangle>50</Triangle>
			<Triangle>50</Triangle>
			<Triangle>52</Triangle>
			<Triangle>51</Triangle>
			<Triangle>48</Triangle>
			<Triangle>51</Triangle>
			<Triangle>52</Triangle>
		</Triangles>
		<Geosets>
			<Geoset triangle="0" triangles="240" />
		</Geosets>
		<Textures>
			<Texture geoset="0" color="-1" blend="0" layer="0" texture="0" transparency="0" />
		</Textures>
	</View>
	<Colors />
	<Textures>
		<Texture type="2" file="" />
	</Textures>
	<Transparencies>
		<Transparency>1</Transparency>
	</Transparencies>
	<Blending>
		<Blend>0</Blend>
	</Blending>
	<Attachments>
		<Attachment id="2" bone="1" />
		<Attachment id="3" bone="2" />
		<Attachment id="4" bone="3" />
	</Attachments>
</Model>