<?xml version="1.0" encoding="utf-8"?>
<Model xmlns:xsi="http://www.w3.org/2001/XMLSchema-instance" xmlns:xsd="http://www.w3.org/2001/XMLSchema">
	<Name>Helm_Leather_A_02_GnF</Name>
	<Bones>
		<Bone>
			<Billboard>0</Billboard>
			<Parent>-1</Parent>
			<Translation x="0" y="0" z="0" />
			<Rotation x="0" y="0" z="-0" w="1" />
			<Scale x="1" y="1" z="1" />
			<Position x="0.0145059" y="-0.07168444" z="0.1079652" />
		</Bone>
	</Bones>
	<Vertices>
		<Vertex>
			<Position x="0.03740897" y="-0.2783272" z="0.1303117" />
			<Bones>
				<Bone index="0" weight="255" />
				<Bone index="0" weight="0" />
				<Bone index="0" weight="0" />
				<Bone index="0" weight="0" />
			</Bones>
			<Normal x="0.3614897" y="-0.9204233" z="0.1488158" />
			<Texture x="0.5873016" y="0.984127" />
		</Vertex>
		<Vertex>
			<Position x="0.1036508" y="-0.226717" z="0.1055819" />
			<Bones>
				<Bone index="0" weight="255" />
				<Bone index="0" weight="0" />
				<Bone index="0" weight="0" />
				<Bone index="0" weight="0" />
			</Bones>
			<Normal x="0.209179" y="-0.9590322" z="0.191053" />
			<Texture x="0.3968254" y="0.984127" />
		</Vertex>
		<Vertex>
			<Position x="0.05723998" y="-0.186059" z="0.1076051" />
			<Bones>
				<Bone index="0" weight="255" />
				<Bone index="0" weight="0" />
				<Bone index="0" weight="0" />
				<Bone index="0" weight="0" />
			</Bones>
			<Normal x="0.5123807" y="-0.8577731" z="0.04112775" />
			<Texture x="0.3968254" y="0.7301587" />
		</Vertex>
		<Vertex>
			<Position x="0.0387389" y="-0.09562923" z="0.09212433" />
			<Bones>
				<Bone index="0" weight="255" />
				<Bone index="0" weight="0" />
				<Bone index="0" weight="0" />
				<Bone index="0" weight="0" />
			</Bones>
			<Normal x="0.7743112" y="-0.6274182" z="0.08239226" />
			<Texture x="0.984127" y="0.8730159" />
		</Vertex>
		<Vertex>
			<Position x="0.01577144" y="-0.06747787" z="0.1167722" />
			<Bones>
				<Bone index="0" weight="255" />
				<Bone index="0" weight="0" />
				<Bone index="0" weight="0" />
				<Bone index="0" weight="0" />
			</Bones>
			<Normal x="0.7019357" y="-0.7101243" z="0.05486134" />
			<Texture x="0.984127" y="0.6507937" />
		</Vertex>
		<Vertex>
			<Position x="0.03328334" y="-0.1020519" z="0.09500492" />
			<Bones>
				<Bone index="0" weight="255" />
				<Bone index="0" weight="0" />
				<Bone index="0" weight="0" />
				<Bone index="0" weight="0" />
			</Bones>
			<Normal x="0.5844063" y="-0.7866211" z="-0.1992399" />
			<Texture x="0.968254" y="0.8730159" />
		</Vertex>
		<Vertex>
			<Position x="0.00377064" y="-0.07977942" z="0.1216575" />
			<Bones>
				<Bone index="0" weight="255" />
				<Bone index="0" weight="0" />
				<Bone index="0" weight="0" />
				<Bone index="0" weight="0" />
			</Bones>
			<Normal x="0.4836719" y="-0.867523" z="-0.1160406" />
			<Texture x="0.9047619" y="0.6507937" />
		</Vertex>
		<Vertex>
			<Position x="-0.03245522" y="-0.01100053" z="0.1443903" />
			<Bones>
				<Bone index="0" weight="255" />
				<Bone index="0" weight="0" />
				<Bone index="0" weight="0" />
				<Bone index="0" weight="0" />
			</Bones>
			<Normal x="0.5086153" y="-0.8478554" z="0.1498384" />
			<Texture x="0.984127" y="0.2698413" />
		</Vertex>
		<Vertex>
			<Position x="-0.04129805" y="-0.02046558" z="0.1483083" />
			<Bones>
				<Bone index="0" weight="255" />
				<Bone index="0" weight="0" />
				<Bone index="0" weight="0" />
				<Bone index="0" weight="0" />
			</Bones>
			<Normal x="0.3533055" y="-0.9338022" z="0.05646839" />
			<Texture x="0.9047619" y="0.2857143" />
		</Vertex>
		<Vertex>
			<Position x="-0.08734623" y="0.05003646" z="0.1477889" />
			<Bones>
				<Bone index="0" weight="255" />
				<Bone index="0" weight="0" />
				<Bone index="0" weight="0" />
				<Bone index="0" weight="0" />
			</Bones>
			<Normal x="0.3472974" y="-0.9003549" z="0.2621939" />
			<Texture x="0.968254" y="0.01587301" />
		</Vertex>
		<Vertex>
			<Position x="-0.02741654" y="0.001898864" z="0.136194" />
			<Bones>
				<Bone index="0" weight="255" />
				<Bone index="0" weight="0" />
				<Bone index="0" weight="0" />
				<Bone index="0" weight="0" />
			</Bones>
			<Normal x="0.5653301" y="-0.778162" z="0.2736159" />
			<Texture x="0.9047619" y="0.2857143" />
		</Vertex>
		<Vertex>
			<Position x="0.01921394" y="-0.05284649" z="0.1065497" />
			<Bones>
				<Bone index="0" weight="255" />
				<Bone index="0" weight="0" />
				<Bone index="0" weight="0" />
				<Bone index="0" weight="0" />
			</Bones>
			<Normal x="0.7466389" y="-0.6298624" z="0.2140181" />
			<Texture x="0.9047619" y="0.6507937" />
		</Vertex>
		<Vertex>
			<Position x="0.03872332" y="-0.08726957" z="0.08547617" />
			<Bones>
				<Bone index="0" weight="255" />
				<Bone index="0" weight="0" />
				<Bone index="0" weight="0" />
				<Bone index="0" weight="0" />
			</Bones>
			<Normal x="0.8492734" y="-0.4664741" z="0.247258" />
			<Texture x="0.968254" y="0.8730159" />
		</Vertex>
		<Vertex>
			<Position x="0.04020221" y="-0.0837492" z="-0.09970497" />
			<Bones>
				<Bone index="0" weight="255" />
				<Bone index="0" weight="0" />
				<Bone index="0" weight="0" />
				<Bone index="0" weight="0" />
			</Bones>
			<Normal x="0.7145107" y="0.6983917" z="-0.04151384" />
			<Texture x="0.8412699" y="1" />
		</Vertex>
		<Vertex>
			<Position x="0.01456769" y="-0.05591776" z="-0.1275855" />
			<Bones>
				<Bone index="0" weight="255" />
				<Bone index="0" weight="0" />
				<Bone index="0" weight="0" />
				<Bone index="0" weight="0" />
			</Bones>
			<Normal x="0.7397988" y="0.6267858" z="0.2446169" />
			<Texture x="0.8253968" y="0.6507937" />
		</Vertex>
		<Vertex>
			<Position x="0.04309059" y="-0.0757108" z="-0.09668531" />
			<Bones>
				<Bone index="0" weight="255" />
				<Bone index="0" weight="0" />
				<Bone index="0" weight="0" />
				<Bone index="0" weight="0" />
			</Bones>
			<Normal x="0.7888896" y="0.5382842" z="0.2964849" />
			<Texture x="0.8571429" y="1" />
		</Vertex>
		<Vertex>
			<Position x="0.007448545" y="-0.07175545" z="-0.1328378" />
			<Bones>
				<Bone index="0" weight="255" />
				<Bone index="0" weight="0" />
				<Bone index="0" weight="0" />
				<Bone index="0" weight="0" />
			</Bones>
			<Normal x="0.6035025" y="0.7973572" z="0.002501028" />
			<Texture x="0.7460318" y="0.6507937" />
		</Vertex>
		<Vertex>
			<Position x="-0.04736855" y="-0.01603834" z="-0.1664653" />
			<Bones>
				<Bone index="0" weight="255" />
				<Bone index="0" weight="0" />
				<Bone index="0" weight="0" />
				<Bone index="0" weight="0" />
			</Bones>
			<Normal x="0.545339" y="0.7931615" z="0.2711093" />
			<Texture x="0.8253968" y="0.2698413" />
		</Vertex>
		<Vertex>
			<Position x="-0.05244641" y="-0.028113" z="-0.1706404" />
			<Bones>
				<Bone index="0" weight="255" />
				<Bone index="0" weight="0" />
				<Bone index="0" weight="0" />
				<Bone index="0" weight="0" />
			</Bones>
			<Normal x="0.4339519" y="0.8920866" z="0.1259654" />
			<Texture x="0.7460318" y="0.2857143" />
		</Vertex>
		<Vertex>
			<Position x="-0.1201783" y="0.0272174" z="-0.1804975" />
			<Bones>
				<Bone index="0" weight="255" />
				<Bone index="0" weight="0" />
				<Bone index="0" weight="0" />
				<Bone index="0" weight="0" />
			</Bones>
			<Normal x="0.3626928" y="0.8724787" z="0.3274672" />
			<Texture x="0.8095238" y="0.01587301" />
		</Vertex>
		<Vertex>
			<Position x="-0.04762084" y="-0.001577514" z="-0.1583734" />
			<Bones>
				<Bone index="0" weight="255" />
				<Bone index="0" weight="0" />
				<Bone index="0" weight="0" />
				<Bone index="0" weight="0" />
			</Bones>
			<Normal x="0.5538124" y="0.7224627" z="0.4139318" />
			<Texture x="0.7460318" y="0.2857143" />
		</Vertex>
		<Vertex>
			<Position x="0.01195698" y="-0.04016185" z="-0.1176287" />
			<Bones>
				<Bone index="0" weight="255" />
				<Bone index="0" weight="0" />
				<Bone index="0" weight="0" />
				<Bone index="0" weight="0" />
			</Bones>
			<Normal x="0.7234243" y="0.5495008" z="0.4179786" />
			<Texture x="0.7460318" y="0.6507937" />
		</Vertex>
		<Vertex>
			<Position x="0.03957127" y="-0.0672726" z="-0.0903175" />
			<Bones>
				<Bone index="0" weight="255" />
				<Bone index="0" weight="0" />
				<Bone index="0" weight="0" />
				<Bone index="0" weight="0" />
			</Bones>
			<Normal x="0.7869661" y="0.3798468" z="0.4862106" />
			<Texture x="0.8412699" y="1" />
		</Vertex>
		<Vertex>
			<Position x="0.06437153" y="-0.09930852" z="-0.08156583" />
			<Bones>
				<Bone index="0" weight="255" />
				<Bone index="0" weight="0" />
				<Bone index="0" weight="0" />
				<Bone index="0" weight="0" />
			</Bones>
			<Normal x="0.6680567" y="0.7441087" z="0.001570831" />
			<Texture x="0.968254" y="0.8730159" />
		</Vertex>
		<Vertex>
			<Position x="0.02627522" y="-0.07817522" z="-0.1157239" />
			<Bones>
				<Bone index="0" weight="255" />
				<Bone index="0" weight="0" />
				<Bone index="0" weight="0" />
				<Bone index="0" weight="0" />
			</Bones>
			<Normal x="0.6390381" y="0.7119958" z="0.2910194" />
			<Texture x="0.984127" y="0.6507937" />
		</Vertex>
		<Vertex>
			<Position x="0.0656253" y="-0.08915538" z="-0.07983356" />
			<Bones>
				<Bone index="0" weight="255" />
				<Bone index="0" weight="0" />
				<Bone index="0" weight="0" />
				<Bone index="0" weight="0" />
			</Bones>
			<Normal x="0.6809695" y="0.6350393" z="0.3646992" />
			<Texture x="0.984127" y="0.8730159" />
		</Vertex>
		<Vertex>
			<Position x="0.02230631" y="-0.09837995" z="-0.1181562" />
			<Bones>
				<Bone index="0" weight="255" />
				<Bone index="0" weight="0" />
				<Bone index="0" weight="0" />
				<Bone index="0" weight="0" />
			</Bones>
			<Normal x="0.5450599" y="0.8383938" z="0.00236218" />
			<Texture x="0.9047619" y="0.6507937" />
		</Vertex>
		<Vertex>
			<Position x="-0.05577615" y="-0.05324923" z="-0.1603897" />
			<Bones>
				<Bone index="0" weight="255" />
				<Bone index="0" weight="0" />
				<Bone index="0" weight="0" />
				<Bone index="0" weight="0" />
			</Bones>
			<Normal x="0.4339964" y="0.865747" z="0.2492573" />
			<Texture x="0.984127" y="0.2698413" />
		</Vertex>
		<Vertex>
			<Position x="-0.05843505" y="-0.06860422" z="-0.1624843" />
			<Bones>
				<Bone index="0" weight="255" />
				<Bone index="0" weight="0" />
				<Bone index="0" weight="0" />
				<Bone index="0" weight="0" />
			</Bones>
			<Normal x="0.3459837" y="0.935792" z="0.06773955" />
			<Texture x="0.9047619" y="0.2857143" />
		</Vertex>
		<Vertex>
			<Position x="-0.1483818" y="-0.02289463" z="-0.1755299" />
			<Bones>
				<Bone index="0" weight="255" />
				<Bone index="0" weight="0" />
				<Bone index="0" weight="0" />
				<Bone index="0" weight="0" />
			</Bones>
			<Normal x="0.236016" y="0.9385274" z="0.2519182" />
			<Texture x="0.968254" y="0.01587301" />
		</Vertex>
		<Vertex>
			<Position x="-0.05923739" y="-0.03574887" z="-0.1535328" />
			<Bones>
				<Bone index="0" weight="255" />
				<Bone index="0" weight="0" />
				<Bone index="0" weight="0" />
				<Bone index="0" weight="0" />
			</Bones>
			<Normal x="0.4179382" y="0.8147467" z="0.40189" />
			<Texture x="0.9047619" y="0.2857143" />
		</Vertex>
		<Vertex>
			<Position x="0.02005313" y="-0.05943545" z="-0.1066492" />
			<Bones>
				<Bone index="0" weight="255" />
				<Bone index="0" weight="0" />
				<Bone index="0" weight="0" />
				<Bone index="0" weight="0" />
			</Bones>
			<Normal x="0.5929973" y="0.6560073" z="0.4669139" />
			<Texture x="0.9047619" y="0.6507937" />
		</Vertex>
		<Vertex>
			<Position x="0.06006743" y="-0.07941691" z="-0.07351729" />
			<Bones>
				<Bone index="0" weight="255" />
				<Bone index="0" weight="0" />
				<Bone index="0" weight="0" />
				<Bone index="0" weight="0" />
			</Bones>
			<Normal x="0.64941" y="0.5031693" z="0.5701643" />
			<Texture x="0.968254" y="0.8730159" />
		</Vertex>
		<Vertex>
			<Position x="0.06810629" y="-0.2123991" z="-0.1057694" />
			<Bones>
				<Bone index="0" weight="255" />
				<Bone index="0" weight="0" />
				<Bone index="0" weight="0" />
				<Bone index="0" weight="0" />
			</Bones>
			<Normal x="0.6623424" y="0.7032609" z="0.258315" />
			<Texture x="0.968254" y="0.8730159" />
		</Vertex>
		<Vertex>
			<Position x="0.07438326" y="-0.256579" z="-0.1160854" />
			<Bones>
				<Bone index="0" weight="255" />
				<Bone index="0" weight="0" />
				<Bone index="0" weight="0" />
				<Bone index="0" weight="0" />
			</Bones>
			<Normal x="0.4520845" y="0.8784674" z="0.1546439" />
			<Texture x="0.984127" y="0.6507937" />
		</Vertex>
		<Vertex>
			<Position x="0.06188304" y="-0.213599" z="-0.111559" />
			<Bones>
				<Bone index="0" weight="255" />
				<Bone index="0" weight="0" />
				<Bone index="0" weight="0" />
				<Bone index="0" weight="0" />
			</Bones>
			<Normal x="0.3527588" y="0.9143332" z="0.198887" />
			<Texture x="0.984127" y="0.8730159" />
		</Vertex>
		<Vertex>
			<Position x="0.08595402" y="-0.2548797" z="-0.1035363" />
			<Bones>
				<Bone index="0" weight="255" />
				<Bone index="0" weight="0" />
				<Bone index="0" weight="0" />
				<Bone index="0" weight="0" />
			</Bones>
			<Normal x="0.7168965" y="0.6877822" z="0.1140833" />
			<Texture x="0.9047619" y="0.6507937" />
		</Vertex>
		<Vertex>
			<Position x="0.08027241" y="-0.3363389" z="-0.1144962" />
			<Bones>
				<Bone index="0" weight="255" />
				<Bone index="0" weight="0" />
				<Bone index="0" weight="0" />
				<Bone index="0" weight="0" />
			</Bones>
			<Normal x="0.5674331" y="0.820385" z="-0.07062622" />
			<Texture x="0.984127" y="0.2698413" />
		</Vertex>
		<Vertex>
			<Position x="0.08926307" y="-0.3348806" z="-0.1052084" />
			<Bones>
				<Bone index="0" weight="255" />
				<Bone index="0" weight="0" />
				<Bone index="0" weight="0" />
				<Bone index="0" weight="0" />
			</Bones>
			<Normal x="0.7226877" y="0.6812313" z="-0.116818" />
			<Texture x="0.9047619" y="0.2857143" />
		</Vertex>
		<Vertex>
			<Position x="0.06341168" y="-0.4147915" z="-0.09972245" />
			<Bones>
				<Bone index="0" weight="255" />
				<Bone index="0" weight="0" />
				<Bone index="0" weight="0" />
				<Bone index="0" weight="0" />
			</Bones>
			<Normal x="0.5938678" y="0.7577868" z="-0.2703335" />
			<Texture x="0.968254" y="0.01587301" />
		</Vertex>
		<Vertex>
			<Position x="0.06644274" y="-0.341033" z="-0.1205552" />
			<Bones>
				<Bone index="0" weight="255" />
				<Bone index="0" weight="0" />
				<Bone index="0" weight="0" />
				<Bone index="0" weight="0" />
			</Bones>
			<Normal x="0.4303562" y="0.8957151" z="-0.1117497" />
			<Texture x="0.9047619" y="0.2857143" />
		</Vertex>
		<Vertex>
			<Position x="0.05818569" y="-0.2627806" z="-0.1208194" />
			<Bones>
				<Bone index="0" weight="255" />
				<Bone index="0" weight="0" />
				<Bone index="0" weight="0" />
				<Bone index="0" weight="0" />
			</Bones>
			<Normal x="0.292405" y="0.9527161" z="0.08265223" />
			<Texture x="0.9047619" y="0.6507937" />
		</Vertex>
		<Vertex>
			<Position x="0.05218278" y="-0.2179074" z="-0.1123984" />
			<Bones>
				<Bone index="0" weight="255" />
				<Bone index="0" weight="0" />
				<Bone index="0" weight="0" />
				<Bone index="0" weight="0" />
			</Bones>
			<Normal x="0.1184198" y="0.9797595" z="0.1613941" />
			<Texture x="0.968254" y="0.8730159" />
		</Vertex>
		<Vertex>
			<Position x="0.07912464" y="-0.2239919" z="0.1096603" />
			<Bones>
				<Bone index="0" weight="255" />
				<Bone index="0" weight="0" />
				<Bone index="0" weight="0" />
				<Bone index="0" weight="0" />
			</Bones>
			<Normal x="0.3780333" y="-0.9150227" z="0.1407984" />
			<Texture x="0.8571429" y="1" />
		</Vertex>
		<Vertex>
			<Position x="0.08527488" y="-0.264107" z="0.1132921" />
			<Bones>
				<Bone index="0" weight="255" />
				<Bone index="0" weight="0" />
				<Bone index="0" weight="0" />
				<Bone index="0" weight="0" />
			</Bones>
			<Normal x="0.4695732" y="-0.8785383" z="0.08758751" />
			<Texture x="0.8253968" y="0.6507937" />
		</Vertex>
		<Vertex>
			<Position x="0.08486085" y="-0.2236499" z="0.104411" />
			<Bones>
				<Bone index="0" weight="255" />
				<Bone index="0" weight="0" />
				<Bone index="0" weight="0" />
				<Bone index="0" weight="0" />
			</Bones>
			<Normal x="0.6914977" y="-0.704064" z="0.1616316" />
			<Texture x="0.8412699" y="1" />
		</Vertex>
		<Vertex>
			<Position x="0.09587721" y="-0.2639488" z="0.1019141" />
			<Bones>
				<Bone index="0" weight="255" />
				<Bone index="0" weight="0" />
				<Bone index="0" weight="0" />
				<Bone index="0" weight="0" />
			</Bones>
			<Normal x="0.7257093" y="-0.6877926" z="0.0169529" />
			<Texture x="0.7460318" y="0.6507937" />
		</Vertex>
		<Vertex>
			<Position x="0.08112954" y="-0.3365021" z="0.1118511" />
			<Bones>
				<Bone index="0" weight="255" />
				<Bone index="0" weight="0" />
				<Bone index="0" weight="0" />
				<Bone index="0" weight="0" />
			</Bones>
			<Normal x="0.5533606" y="-0.8203846" z="-0.1440873" />
			<Texture x="0.8253968" y="0.2698413" />
		</Vertex>
		<Vertex>
			<Position x="0.08938404" y="-0.3362552" z="0.1034302" />
			<Bones>
				<Bone index="0" weight="255" />
				<Bone index="0" weight="0" />
				<Bone index="0" weight="0" />
				<Bone index="0" weight="0" />
			</Bones>
			<Normal x="0.7012573" y="-0.681231" z="-0.2101486" />
			<Texture x="0.7460318" y="0.2857143" />
		</Vertex>
		<Vertex>
			<Position x="0.05668855" y="-0.4050295" z="0.09845609" />
			<Bones>
				<Bone index="0" weight="255" />
				<Bone index="0" weight="0" />
				<Bone index="0" weight="0" />
				<Bone index="0" weight="0" />
			</Bones>
			<Normal x="0.553502" y="-0.7577863" z="-0.3455364" />
			<Texture x="0.8095238" y="0.01587301" />
		</Vertex>
		<Vertex>
			<Position x="0.06814222" y="-0.339085" z="0.1173447" />
			<Bones>
				<Bone index="0" weight="255" />
				<Bone index="0" weight="0" />
				<Bone index="0" weight="0" />
				<Bone index="0" weight="0" />
			</Bones>
			<Normal x="0.412089" y="-0.8957147" z="-0.1669668" />
			<Texture x="0.7460318" y="0.2857143" />
		</Vertex>
		<Vertex>
			<Position x="0.0699806" y="-0.2677649" z="0.1175843" />
			<Bones>
				<Bone index="0" weight="255" />
				<Bone index="0" weight="0" />
				<Bone index="0" weight="0" />
				<Bone index="0" weight="0" />
			</Bones>
			<Normal x="0.3015124" y="-0.9526172" z="0.04013347" />
			<Texture x="0.7460318" y="0.6507937" />
		</Vertex>
		<Vertex>
			<Position x="0.06989498" y="-0.226717" z="0.1104213" />
			<Bones>
				<Bone index="0" weight="255" />
				<Bone index="0" weight="0" />
				<Bone index="0" weight="0" />
				<Bone index="0" weight="0" />
			</Bones>
			<Normal x="0.1416284" y="-0.9808677" z="0.1335663" />
			<Texture x="0.8412699" y="1" />
		</Vertex>
		<Vertex>
			<Position x="0.06873338" y="-0.2397791" z="-0.1121483" />
			<Bones>
				<Bone index="0" weight="255" />
				<Bone index="0" weight="0" />
				<Bone index="0" weight="0" />
				<Bone index="0" weight="0" />
			</Bones>
			<Normal x="0.6608397" y="0.6737675" z="0.3306482" />
			<Texture x="0.8412699" y="1" />
		</Vertex>
		<Vertex>
			<Position x="0.06899481" y="-0.2747866" z="-0.1290717" />
			<Bones>
				<Bone index="0" weight="255" />
				<Bone index="0" weight="0" />
				<Bone index="0" weight="0" />
				<Bone index="0" weight="0" />
			</Bones>
			<Normal x="0.4299942" y="0.854745" z="0.2907164" />
			<Texture x="0.8253968" y="0.6507937" />
		</Vertex>
		<Vertex>
			<Position x="0.06298076" y="-0.2388259" z="-0.1168575" />
			<Bones>
				<Bone index="0" weight="255" />
				<Bone index="0" weight="0" />
				<Bone index="0" weight="0" />
				<Bone index="0" weight="0" />
			</Bones>
			<Normal x="0.3365096" y="0.8730853" z="0.3528219" />
			<Texture x="0.8571429" y="1" />
		</Vertex>
		<Vertex>
			<Position x="0.07972198" y="-0.2774304" z="-0.1189132" />
			<Bones>
				<Bone index="0" weight="255" />
				<Bone index="0" weight="0" />
				<Bone index="0" weight="0" />
				<Bone index="0" weight="0" />
			</Bones>
			<Normal x="0.6935346" y="0.6973456" z="0.1808835" />
			<Texture x="0.7460318" y="0.6507937" />
		</Vertex>
		<Vertex>
			<Position x="0.0657791" y="-0.3423322" z="-0.1423424" />
			<Bones>
				<Bone index="0" weight="255" />
				<Bone index="0" weight="0" />
				<Bone index="0" weight="0" />
				<Bone index="0" weight="0" />
			</Bones>
			<Normal x="0.5136679" y="0.8566775" z="0.04742167" />
			<Texture x="0.8253968" y="0.2698413" />
		</Vertex>
		<Vertex>
			<Position x="0.07410612" y="-0.3441603" z="-0.1348131" />
			<Bones>
				<Bone index="0" weight="255" />
				<Bone index="0" weight="0" />
				<Bone index="0" weight="0" />
				<Bone index="0" weight="0" />
			</Bones>
			<Normal x="0.6649597" y="0.7456803" z="-0.04230168" />
			<Texture x="0.7460318" y="0.2857143" />
		</Vertex>
		<Vertex>
			<Position x="0.04380668" y="-0.4098654" z="-0.1429837" />
			<Bones>
				<Bone index="0" weight="255" />
				<Bone index="0" weight="0" />
				<Bone index="0" weight="0" />
				<Bone index="0" weight="0" />
			</Bones>
			<Normal x="0.5135614" y="0.8431767" z="-0.1590842" />
			<Texture x="0.8095238" y="0.01587301" />
		</Vertex>
		<Vertex>
			<Position x="0.05311527" y="-0.3435384" z="-0.1474575" />
			<Bones>
				<Bone index="0" weight="255" />
				<Bone index="0" weight="0" />
				<Bone index="0" weight="0" />
				<Bone index="0" weight="0" />
			</Bones>
			<Normal x="0.3710832" y="0.9278005" z="0.03851662" />
			<Texture x="0.7460318" y="0.2857143" />
		</Vertex>
		<Vertex>
			<Position x="0.05420431" y="-0.2773531" z="-0.1332058" />
			<Bones>
				<Bone index="0" weight="255" />
				<Bone index="0" weight="0" />
				<Bone index="0" weight="0" />
				<Bone index="0" weight="0" />
			</Bones>
			<Normal x="0.2597332" y="0.9317705" z="0.253658" />
			<Texture x="0.7460318" y="0.6507937" />
		</Vertex>
		<Vertex>
			<Position x="0.05415832" y="-0.2413375" z="-0.1177648" />
			<Bones>
				<Bone index="0" weight="255" />
				<Bone index="0" weight="0" />
				<Bone index="0" weight="0" />
				<Bone index="0" weight="0" />
			</Bones>
			<Normal x="0.09583319" y="0.9293118" z="0.3566449" />
			<Texture x="0.8412699" y="1" />
		</Vertex>
		<Vertex>
			<Position x="0.04335595" y="-0.08686575" z="0.09230614" />
			<Bones>
				<Bone index="0" weight="255" />
				<Bone index="0" weight="0" />
				<Bone index="0" weight="0" />
				<Bone index="0" weight="0" />
			</Bones>
			<Normal x="0.5930531" y="-0.7980409" z="0.106859" />
			<Texture x="0.8571429" y="1" />
		</Vertex>
		<Vertex>
			<Position x="-0.0006833815" y="-0.07337689" z="0.1232272" />
			<Bones>
				<Bone index="0" weight="255" />
				<Bone index="0" weight="0" />
				<Bone index="0" weight="0" />
				<Bone index="0" weight="0" />
			</Bones>
			<Normal x="0.5743942" y="-0.7917113" z="0.2080012" />
			<Texture x="0.8253968" y="0.6507937" />
		</Vertex>
		<Vertex>
			<Position x="0.03992216" y="-0.09686438" z="0.09177813" />
			<Bones>
				<Bone index="0" weight="255" />
				<Bone index="0" weight="0" />
				<Bone index="0" weight="0" />
				<Bone index="0" weight="0" />
			</Bones>
			<Normal x="0.6308354" y="-0.7740209" z="0.05420701" />
			<Texture x="0.8412699" y="1" />
		</Vertex>
		<Vertex>
			<Position x="0.02016726" y="-0.1131509" z="0.1209263" />
			<Bones>
				<Bone index="0" weight="255" />
				<Bone index="0" weight="0" />
				<Bone index="0" weight="0" />
				<Bone index="0" weight="0" />
			</Bones>
			<Normal x="0.4705696" y="-0.8749782" z="0.1139183" />
			<Texture x="0.7460318" y="0.6507937" />
		</Vertex>
		<Vertex>
			<Position x="-0.08594705" y="-0.03836956" z="0.1583561" />
			<Bones>
				<Bone index="0" weight="255" />
				<Bone index="0" weight="0" />
				<Bone index="0" weight="0" />
				<Bone index="0" weight="0" />
			</Bones>
			<Normal x="0.2970868" y="-0.950902" z="0.08674595" />
			<Texture x="0.8253968" y="0.2698413" />
		</Vertex>
		<Vertex>
			<Position x="-0.09178174" y="-0.05324122" z="0.1569106" />
			<Bones>
				<Bone index="0" weight="255" />
				<Bone index="0" weight="0" />
				<Bone index="0" weight="0" />
				<Bone index="0" weight="0" />
			</Bones>
			<Normal x="0.1109134" y="-0.9840387" z="-0.1391624" />
			<Texture x="0.7460318" y="0.2857143" />
		</Vertex>
		<Vertex>
			<Position x="-0.1745305" y="0.009035725" z="0.1636668" />
			<Bones>
				<Bone index="0" weight="255" />
				<Bone index="0" weight="0" />
				<Bone index="0" weight="0" />
				<Bone index="0" weight="0" />
			</Bones>
			<Normal x="0.08328771" y="-0.9955491" z="0.04410472" />
			<Texture x="0.8095238" y="0.01587301" />
		</Vertex>
		<Vertex>
			<Position x="-0.08475782" y="-0.01929524" z="0.1544977" />
			<Bones>
				<Bone index="0" weight="255" />
				<Bone index="0" weight="0" />
				<Bone index="0" weight="0" />
				<Bone index="0" weight="0" />
			</Bones>
			<Normal x="0.3101595" y="-0.9353839" z="0.1698763" />
			<Texture x="0.7460318" y="0.2857143" />
		</Vertex>
		<Vertex>
			<Position x="-0.001526092" y="-0.05212822" z="0.1169618" />
			<Bones>
				<Bone index="0" weight="255" />
				<Bone index="0" weight="0" />
				<Bone index="0" weight="0" />
				<Bone index="0" weight="0" />
			</Bones>
			<Normal x="0.5223178" y="-0.8236903" z="0.2207225" />
			<Texture x="0.7460318" y="0.6507937" />
		</Vertex>
		<Vertex>
			<Position x="0.04096273" y="-0.07506265" z="0.08707869" />
			<Bones>
				<Bone index="0" weight="255" />
				<Bone index="0" weight="0" />
				<Bone index="0" weight="0" />
				<Bone index="0" weight="0" />
			</Bones>
			<Normal x="0.6258239" y="-0.7054908" z="0.3326067" />
			<Texture x="0.8412699" y="1" />
		</Vertex>
		<Vertex>
			<Position x="0.08429825" y="-0.2247885" z="0.1045943" />
			<Bones>
				<Bone index="0" weight="255" />
				<Bone index="0" weight="0" />
				<Bone index="0" weight="0" />
				<Bone index="0" weight="0" />
			</Bones>
			<Normal x="0.2890626" y="-0.8822042" z="0.371697" />
			<Texture x="0.984127" y="0.8730159" />
		</Vertex>
		<Vertex>
			<Position x="0.07872812" y="-0.2532047" z="0.1183919" />
			<Bones>
				<Bone index="0" weight="255" />
				<Bone index="0" weight="0" />
				<Bone index="0" weight="0" />
				<Bone index="0" weight="0" />
			</Bones>
			<Normal x="0.3618568" y="-0.8863269" z="0.2889366" />
			<Texture x="0.984127" y="0.6507937" />
		</Vertex>
		<Vertex>
			<Position x="0.08943494" y="-0.2275743" z="0.101639" />
			<Bones>
				<Bone index="0" weight="255" />
				<Bone index="0" weight="0" />
				<Bone index="0" weight="0" />
				<Bone index="0" weight="0" />
			</Bones>
			<Normal x="0.6130032" y="-0.7538092" z="0.2366407" />
			<Texture x="0.968254" y="0.8730159" />
		</Vertex>
		<Vertex>
			<Position x="0.08831359" y="-0.2593299" z="0.1118204" />
			<Bones>
				<Bone index="0" weight="255" />
				<Bone index="0" weight="0" />
				<Bone index="0" weight="0" />
				<Bone index="0" weight="0" />
			</Bones>
			<Normal x="0.5973307" y="-0.7960626" z="0.09736675" />
			<Texture x="0.9047619" y="0.6507937" />
		</Vertex>
		<Vertex>
			<Position x="0.05806127" y="-0.3050725" z="0.1350352" />
			<Bones>
				<Bone index="0" weight="255" />
				<Bone index="0" weight="0" />
				<Bone index="0" weight="0" />
				<Bone index="0" weight="0" />
			</Bones>
			<Normal x="0.3723451" y="-0.9270075" z="0.04490247" />
			<Texture x="0.984127" y="0.2698413" />
		</Vertex>
		<Vertex>
			<Position x="0.06550027" y="-0.3095865" z="0.1302084" />
			<Bones>
				<Bone index="0" weight="255" />
				<Bone index="0" weight="0" />
				<Bone index="0" weight="0" />
				<Bone index="0" weight="0" />
			</Bones>
			<Normal x="0.5015587" y="-0.8600964" z="-0.09312912" />
			<Texture x="0.9047619" y="0.2857143" />
		</Vertex>
		<Vertex>
			<Position x="0.02422812" y="-0.3550047" z="0.1384387" />
			<Bones>
				<Bone index="0" weight="255" />
				<Bone index="0" weight="0" />
				<Bone index="0" weight="0" />
				<Bone index="0" weight="0" />
			</Bones>
			<Normal x="0.3162777" y="-0.936659" z="-0.1504605" />
			<Texture x="0.968254" y="0.01587301" />
		</Vertex>
		<Vertex>
			<Position x="0.0467793" y="-0.3024892" z="0.1374954" />
			<Bones>
				<Bone index="0" weight="255" />
				<Bone index="0" weight="0" />
				<Bone index="0" weight="0" />
				<Bone index="0" weight="0" />
			</Bones>
			<Normal x="0.2302617" y="-0.9696542" z="0.08216024" />
			<Texture x="0.9047619" y="0.2857143" />
		</Vertex>
		<Vertex>
			<Position x="0.06556066" y="-0.251431" z="0.1198479" />
			<Bones>
				<Bone index="0" weight="255" />
				<Bone index="0" weight="0" />
				<Bone index="0" weight="0" />
				<Bone index="0" weight="0" />
			</Bones>
			<Normal x="0.1862247" y="-0.9314877" z="0.3124914" />
			<Texture x="0.9047619" y="0.6507937" />
		</Vertex>
		<Vertex>
			<Position x="0.07645165" y="-0.224784" z="0.1042621" />
			<Bones>
				<Bone index="0" weight="255" />
				<Bone index="0" weight="0" />
				<Bone index="0" weight="0" />
				<Bone index="0" weight="0" />
			</Bones>
			<Normal x="0.06034493" y="-0.8918725" z="0.4482432" />
			<Texture x="0.968254" y="0.8730159" />
		</Vertex>
		<Vertex>
			<Position x="0.1039942" y="-0.222925" z="-0.1091008" />
			<Bones>
				<Bone index="0" weight="255" />
				<Bone index="0" weight="0" />
				<Bone index="0" weight="0" />
				<Bone index="0" weight="0" />
			</Bones>
			<Normal x="0.1149889" y="0.9748632" z="0.1908381" />
			<Texture x="0.3968254" y="0.984127" />
		</Vertex>
		<Vertex>
			<Position x="0.03740897" y="-0.2783272" z="-0.1278003" />
			<Bones>
				<Bone index="0" weight="255" />
				<Bone index="0" weight="0" />
				<Bone index="0" weight="0" />
				<Bone index="0" weight="0" />
			</Bones>
			<Normal x="0.2570906" y="0.9537729" z="0.1556332" />
			<Texture x="0.5873016" y="0.984127" />
		</Vertex>
		<Vertex>
			<Position x="0.05723996" y="-0.186059" z="-0.1073989" />
			<Bones>
				<Bone index="0" weight="255" />
				<Bone index="0" weight="0" />
				<Bone index="0" weight="0" />
				<Bone index="0" weight="0" />
			</Bones>
			<Normal x="0.4706553" y="0.8822418" z="0.01153145" />
			<Texture x="0.3968254" y="0.7301587" />
		</Vertex>
		<Vertex>
			<Position x="0.01164192" y="-0.223639" z="-0.1319034" />
			<Bones>
				<Bone index="0" weight="255" />
				<Bone index="0" weight="0" />
				<Bone index="0" weight="0" />
				<Bone index="0" weight="0" />
			</Bones>
			<Normal x="0.4869589" y="0.8731602" z="-0.02149962" />
			<Texture x="0.6507937" y="0.8888889" />
		</Vertex>
		<Vertex>
			<Position x="-0.001496189" y="-0.1807413" z="-0.1495513" />
			<Bones>
				<Bone index="0" weight="255" />
				<Bone index="0" weight="0" />
				<Bone index="0" weight="0" />
				<Bone index="0" weight="0" />
			</Bones>
			<Normal x="0.5710747" y="0.8114311" z="-0.1243112" />
			<Texture x="0.6984127" y="0.7301587" />
		</Vertex>
		<Vertex>
			<Position x="0.003459516" y="-0.1284963" z="-0.151768" />
			<Bones>
				<Bone index="0" weight="255" />
				<Bone index="0" weight="0" />
				<Bone index="0" weight="0" />
				<Bone index="0" weight="0" />
			</Bones>
			<Normal x="0.5953633" y="0.8007241" z="0.06620818" />
			<Texture x="0.6984127" y="0.4920635" />
		</Vertex>
		<Vertex>
			<Position x="0.05819782" y="-0.1260691" z="-0.1068795" />
			<Bones>
				<Bone index="0" weight="255" />
				<Bone index="0" weight="0" />
				<Bone index="0" weight="0" />
				<Bone index="0" weight="0" />
			</Bones>
			<Normal x="0.6340054" y="0.7733201" z="0.003631052" />
			<Texture x="0.3968254" y="0.4920635" />
		</Vertex>
		<Vertex>
			<Position x="0.06492801" y="-0.1008345" z="-0.1010155" />
			<Bones>
				<Bone index="0" weight="255" />
				<Bone index="0" weight="0" />
				<Bone index="0" weight="0" />
				<Bone index="0" weight="0" />
			</Bones>
			<Normal x="0.4878796" y="0.8507" z="0.1956603" />
			<Texture x="0.3968254" y="0.3333333" />
		</Vertex>
		<Vertex>
			<Position x="0.122333" y="-0.09443349" z="-0.07180039" />
			<Bones>
				<Bone index="0" weight="255" />
				<Bone index="0" weight="0" />
				<Bone index="0" weight="0" />
				<Bone index="0" weight="0" />
			</Bones>
			<Normal x="0.7163331" y="0.6039738" z="0.3494031" />
			<Texture x="0.3174603" y="0.3333333" />
		</Vertex>
		<Vertex>
			<Position x="0.1681179" y="-0.09195518" z="0.0007583231" />
			<Bones>
				<Bone index="0" weight="255" />
				<Bone index="0" weight="0" />
				<Bone index="0" weight="0" />
				<Bone index="0" weight="0" />
			</Bones>
			<Normal x="0.9162383" y="-2.847439E-08" z="0.4006337" />
			<Texture x="0.02376723" y="0.3333333" />
		</Vertex>
		<Vertex>
			<Position x="0.1529469" y="-0.1290335" z="-0.06050143" />
			<Bones>
				<Bone index="0" weight="255" />
				<Bone index="0" weight="0" />
				<Bone index="0" weight="0" />
				<Bone index="0" weight="0" />
			</Bones>
			<Normal x="0.8371295" y="0.4196695" z="0.3508443" />
			<Texture x="0.3015873" y="0.6349206" />
		</Vertex>
		<Vertex>
			<Position x="0.1828981" y="-0.1596775" z="0.0007583236" />
			<Bones>
				<Bone index="0" weight="255" />
				<Bone index="0" weight="0" />
				<Bone index="0" weight="0" />
				<Bone index="0" weight="0" />
			</Bones>
			<Normal x="0.9770024" y="-2.552429E-08" z="0.2132283" />
			<Texture x="0.02376723" y="0.7460318" />
		</Vertex>
		<Vertex>
			<Position x="0.1529469" y="-0.1290335" z="0.06201806" />
			<Bones>
				<Bone index="0" weight="255" />
				<Bone index="0" weight="0" />
				<Bone index="0" weight="0" />
				<Bone index="0" weight="0" />
			</Bones>
			<Normal x="0.8371294" y="-0.4196696" z="0.3508444" />
			<Texture x="0.3015873" y="0.6349206" />
		</Vertex>
		<Vertex>
			<Position x="0.122333" y="-0.09443349" z="0.07331703" />
			<Bones>
				<Bone index="0" weight="255" />
				<Bone index="0" weight="0" />
				<Bone index="0" weight="0" />
				<Bone index="0" weight="0" />
			</Bones>
			<Normal x="0.7163332" y="-0.6039737" z="0.3494029" />
			<Texture x="0.3174603" y="0.3333333" />
		</Vertex>
		<Vertex>
			<Position x="0.1409431" y="-0.03481486" z="0.0007583239" />
			<Bones>
				<Bone index="0" weight="255" />
				<Bone index="0" weight="0" />
				<Bone index="0" weight="0" />
				<Bone index="0" weight="0" />
			</Bones>
			<Normal x="0.920858" y="1.646773E-08" z="0.3898982" />
			<Texture x="0.02376723" y="0.01587301" />
		</Vertex>
		<Vertex>
			<Position x="0.104296" y="-0.04406624" z="-0.0703557" />
			<Bones>
				<Bone index="0" weight="255" />
				<Bone index="0" weight="0" />
				<Bone index="0" weight="0" />
				<Bone index="0" weight="0" />
			</Bones>
			<Normal x="0.5636958" y="0.785981" z="0.2539309" />
			<Texture x="0.3174603" y="0.01587301" />
		</Vertex>
		<Vertex>
			<Position x="0.02830698" y="-0.04929382" z="-0.1019145" />
			<Bones>
				<Bone index="0" weight="255" />
				<Bone index="0" weight="0" />
				<Bone index="0" weight="0" />
				<Bone index="0" weight="0" />
			</Bones>
			<Normal x="0.4323547" y="0.8530051" z="0.2923214" />
			<Texture x="0.6984127" y="0.01587301" />
		</Vertex>
		<Vertex>
			<Position x="0.104296" y="-0.04406624" z="0.07187235" />
			<Bones>
				<Bone index="0" weight="255" />
				<Bone index="0" weight="0" />
				<Bone index="0" weight="0" />
				<Bone index="0" weight="0" />
			</Bones>
			<Normal x="0.563696" y="-0.7859809" z="0.2539307" />
			<Texture x="0.3174603" y="0.01587301" />
		</Vertex>
		<Vertex>
			<Position x="0.06492803" y="-0.1008345" z="0.1025322" />
			<Bones>
				<Bone index="0" weight="255" />
				<Bone index="0" weight="0" />
				<Bone index="0" weight="0" />
				<Bone index="0" weight="0" />
			</Bones>
			<Normal x="0.4703501" y="-0.8608487" z="0.1941916" />
			<Texture x="0.3968254" y="0.3333333" />
		</Vertex>
		<Vertex>
			<Position x="0.02830699" y="-0.04929382" z="0.1034312" />
			<Bones>
				<Bone index="0" weight="255" />
				<Bone index="0" weight="0" />
				<Bone index="0" weight="0" />
				<Bone index="0" weight="0" />
			</Bones>
			<Normal x="0.4190246" y="-0.8628508" z="0.2826779" />
			<Texture x="0.6984127" y="0.01587301" />
		</Vertex>
		<Vertex>
			<Position x="0.00345952" y="-0.1276662" z="0.1490488" />
			<Bones>
				<Bone index="0" weight="255" />
				<Bone index="0" weight="0" />
				<Bone index="0" weight="0" />
				<Bone index="0" weight="0" />
			</Bones>
			<Normal x="0.5753236" y="-0.8138396" z="0.08165671" />
			<Texture x="0.6984127" y="0.4920635" />
		</Vertex>
		<Vertex>
			<Position x="0.05819785" y="-0.1260691" z="0.1083398" />
			<Bones>
				<Bone index="0" weight="255" />
				<Bone index="0" weight="0" />
				<Bone index="0" weight="0" />
				<Bone index="0" weight="0" />
			</Bones>
			<Normal x="0.5966982" y="-0.8024595" z="0.00318186" />
			<Texture x="0.3968254" y="0.4920635" />
		</Vertex>
		<Vertex>
			<Position x="-0.001496183" y="-0.1807413" z="0.1522846" />
			<Bones>
				<Bone index="0" weight="255" />
				<Bone index="0" weight="0" />
				<Bone index="0" weight="0" />
				<Bone index="0" weight="0" />
			</Bones>
			<Normal x="0.6029509" y="-0.796956" z="-0.03621272" />
			<Texture x="0.6984127" y="0.7301587" />
		</Vertex>
		<Vertex>
			<Position x="0.01164193" y="-0.2236391" z="0.138918" />
			<Bones>
				<Bone index="0" weight="255" />
				<Bone index="0" weight="0" />
				<Bone index="0" weight="0" />
				<Bone index="0" weight="0" />
			</Bones>
			<Normal x="0.5551886" y="-0.8315031" z="0.0191908" />
			<Texture x="0.6507937" y="0.8888889" />
		</Vertex>
	</Vertices>
	<View>
		<Indices>
			<Index>0</Index>
			<Index>1</Index>
			<Index>2</Index>
			<Index>3</Index>
			<Index>4</Index>
			<Index>5</Index>
			<Index>6</Index>
			<Index>7</Index>
			<Index>8</Index>
			<Index>9</Index>
			<Index>10</Index>
			<Index>11</Index>
			<Index>12</Index>
			<Index>13</Index>
			<Index>14</Index>
			<Index>15</Index>
			<Index>16</Index>
			<Index>17</Index>
			<Index>18</Index>
			<Index>19</Index>
			<Index>20</Index>
			<Index>21</Index>
			<Index>22</Index>
			<Index>23</Index>
			<Index>24</Index>
			<Index>25</Index>
			<Index>26</Index>
			<Index>27</Index>
			<Index>28</Index>
			<Index>29</Index>
			<Index>30</Index>
			<Index>31</Index>
			<Index>32</Index>
			<Index>33</Index>
			<Index>34</Index>
			<Index>35</Index>
			<Index>36</Index>
			<Index>37</Index>
			<Index>38</Index>
			<Index>39</Index>
			<Index>40</Index>
			<Index>41</Index>
			<Index>42</Index>
			<Index>43</Index>
			<Index>44</Index>
			<Index>45</Index>
			<Index>46</Index>
			<Index>47</Index>
			<Index>48</Index>
			<Index>49</Index>
			<Index>50</Index>
			<Index>51</Index>
			<Index>52</Index>
			<Index>53</Index>
			<Index>54</Index>
			<Index>55</Index>
			<Index>56</Index>
			<Index>57</Index>
			<Index>58</Index>
			<Index>59</Index>
			<Index>60</Index>
			<Index>61</Index>
			<Index>62</Index>
			<Index>63</Index>
			<Index>64</Index>
			<Index>65</Index>
			<Index>66</Index>
			<Index>67</Index>
			<Index>68</Index>
			<Index>69</Index>
			<Index>70</Index>
			<Index>71</Index>
			<Index>72</Index>
			<Index>73</Index>
			<Index>74</Index>
			<Index>75</Index>
			<Index>76</Index>
			<Index>77</Index>
			<Index>78</Index>
			<Index>79</Index>
			<Index>80</Index>
			<Index>81</Index>
			<Index>82</Index>
			<Index>83</Index>
			<Index>84</Index>
			<Index>85</Index>
			<Index>86</Index>
			<Index>87</Index>
			<Index>88</Index>
			<Index>89</Index>
			<Index>90</Index>
			<Index>91</Index>
			<Index>92</Index>
			<Index>93</Index>
			<Index>94</Index>
			<Index>95</Index>
			<Index>96</Index>
			<Index>97</Index>
			<Index>98</Index>
			<Index>99</Index>
			<Index>100</Index>
			<Index>101</Index>
			<Index>102</Index>
			<Index>103</Index>
			<Index>104</Index>
			<Index>105</Index>
			<Index>106</Index>
		</Indices>
		<Triangles>
			<Triangle>83</Triangle>
			<Triangle>84</Triangle>
			<Triangle>85</Triangle>
			<Triangle>84</Triangle>
			<Triangle>86</Triangle>
			<Triangle>85</Triangle>
			<Triangle>87</Triangle>
			<Triangle>85</Triangle>
			<Triangle>86</Triangle>
			<Triangle>87</Triangle>
			<Triangle>88</Triangle>
			<Triangle>85</Triangle>
			<Triangle>88</Triangle>
			<Triangle>89</Triangle>
			<Triangle>85</Triangle>
			<Triangle>89</Triangle>
			<Triangle>88</Triangle>
			<Triangle>90</Triangle>
			<Triangle>90</Triangle>
			<Triangle>88</Triangle>
			<Triangle>99</Triangle>
			<Triangle>90</Triangle>
			<Triangle>99</Triangle>
			<Triangle>98</Triangle>
			<Triangle>91</Triangle>
			<Triangle>90</Triangle>
			<Triangle>98</Triangle>
			<Triangle>91</Triangle>
			<Triangle>98</Triangle>
			<Triangle>97</Triangle>
			<Triangle>91</Triangle>
			<Triangle>97</Triangle>
			<Triangle>92</Triangle>
			<Triangle>91</Triangle>
			<Triangle>92</Triangle>
			<Triangle>93</Triangle>
			<Triangle>92</Triangle>
			<Triangle>94</Triangle>
			<Triangle>93</Triangle>
			<Triangle>92</Triangle>
			<Triangle>95</Triangle>
			<Triangle>94</Triangle>
			<Triangle>96</Triangle>
			<Triangle>95</Triangle>
			<Triangle>92</Triangle>
			<Triangle>96</Triangle>
			<Triangle>92</Triangle>
			<Triangle>97</Triangle>
			<Triangle>96</Triangle>
			<Triangle>97</Triangle>
			<Triangle>100</Triangle>
			<Triangle>96</Triangle>
			<Triangle>100</Triangle>
			<Triangle>101</Triangle>
			<Triangle>101</Triangle>
			<Triangle>100</Triangle>
			<Triangle>102</Triangle>
			<Triangle>101</Triangle>
			<Triangle>102</Triangle>
			<Triangle>103</Triangle>
			<Triangle>104</Triangle>
			<Triangle>101</Triangle>
			<Triangle>103</Triangle>
			<Triangle>103</Triangle>
			<Triangle>2</Triangle>
			<Triangle>104</Triangle>
			<Triangle>105</Triangle>
			<Triangle>2</Triangle>
			<Triangle>103</Triangle>
			<Triangle>105</Triangle>
			<Triangle>106</Triangle>
			<Triangle>2</Triangle>
			<Triangle>0</Triangle>
			<Triangle>2</Triangle>
			<Triangle>106</Triangle>
			<Triangle>0</Triangle>
			<Triangle>1</Triangle>
			<Triangle>2</Triangle>
			<Triangle>74</Triangle>
			<Triangle>73</Triangle>
			<Triangle>82</Triangle>
			<Triangle>73</Triangle>
			<Triangle>74</Triangle>
			<Triangle>75</Triangle>
			<Triangle>74</Triangle>
			<Triangle>76</Triangle>
			<Triangle>75</Triangle>
			<Triangle>74</Triangle>
			<Triangle>77</Triangle>
			<Triangle>76</Triangle>
			<Triangle>77</Triangle>
			<Triangle>78</Triangle>
			<Triangle>76</Triangle>
			<Triangle>78</Triangle>
			<Triangle>77</Triangle>
			<Triangle>79</Triangle>
			<Triangle>77</Triangle>
			<Triangle>80</Triangle>
			<Triangle>79</Triangle>
			<Triangle>74</Triangle>
			<Triangle>82</Triangle>
			<Triangle>81</Triangle>
			<Triangle>77</Triangle>
			<Triangle>74</Triangle>
			<Triangle>81</Triangle>
			<Triangle>77</Triangle>
			<Triangle>81</Triangle>
			<Triangle>80</Triangle>
			<Triangle>64</Triangle>
			<Triangle>63</Triangle>
			<Triangle>72</Triangle>
			<Triangle>63</Triangle>
			<Triangle>64</Triangle>
			<Triangle>65</Triangle>
			<Triangle>64</Triangle>
			<Triangle>66</Triangle>
			<Triangle>65</Triangle>
			<Triangle>64</Triangle>
			<Triangle>67</Triangle>
			<Triangle>66</Triangle>
			<Triangle>67</Triangle>
			<Triangle>68</Triangle>
			<Triangle>66</Triangle>
			<Triangle>68</Triangle>
			<Triangle>67</Triangle>
			<Triangle>69</Triangle>
			<Triangle>67</Triangle>
			<Triangle>70</Triangle>
			<Triangle>69</Triangle>
			<Triangle>64</Triangle>
			<Triangle>72</Triangle>
			<Triangle>71</Triangle>
			<Triangle>67</Triangle>
			<Triangle>64</Triangle>
			<Triangle>71</Triangle>
			<Triangle>67</Triangle>
			<Triangle>71</Triangle>
			<Triangle>70</Triangle>
			<Triangle>62</Triangle>
			<Triangle>55</Triangle>
			<Triangle>54</Triangle>
			<Triangle>53</Triangle>
			<Triangle>54</Triangle>
			<Triangle>55</Triangle>
			<Triangle>53</Triangle>
			<Triangle>56</Triangle>
			<Triangle>54</Triangle>
			<Triangle>56</Triangle>
			<Triangle>57</Triangle>
			<Triangle>54</Triangle>
			<Triangle>61</Triangle>
			<Triangle>54</Triangle>
			<Triangle>57</Triangle>
			<Triangle>61</Triangle>
			<Triangle>62</Triangle>
			<Triangle>54</Triangle>
			<Triangle>56</Triangle>
			<Triangle>58</Triangle>
			<Triangle>57</Triangle>
			<Triangle>59</Triangle>
			<Triangle>57</Triangle>
			<Triangle>58</Triangle>
			<Triangle>59</Triangle>
			<Triangle>60</Triangle>
			<Triangle>57</Triangle>
			<Triangle>60</Triangle>
			<Triangle>61</Triangle>
			<Triangle>57</Triangle>
			<Triangle>44</Triangle>
			<Triangle>43</Triangle>
			<Triangle>52</Triangle>
			<Triangle>43</Triangle>
			<Triangle>44</Triangle>
			<Triangle>45</Triangle>
			<Triangle>44</Triangle>
			<Triangle>46</Triangle>
			<Triangle>45</Triangle>
			<Triangle>44</Triangle>
			<Triangle>47</Triangle>
			<Triangle>46</Triangle>
			<Triangle>47</Triangle>
			<Triangle>48</Triangle>
			<Triangle>46</Triangle>
			<Triangle>48</Triangle>
			<Triangle>47</Triangle>
			<Triangle>49</Triangle>
			<Triangle>47</Triangle>
			<Triangle>50</Triangle>
			<Triangle>49</Triangle>
			<Triangle>44</Triangle>
			<Triangle>52</Triangle>
			<Triangle>51</Triangle>
			<Triangle>47</Triangle>
			<Triangle>44</Triangle>
			<Triangle>51</Triangle>
			<Triangle>47</Triangle>
			<Triangle>51</Triangle>
			<Triangle>50</Triangle>
			<Triangle>42</Triangle>
			<Triangle>35</Triangle>
			<Triangle>34</Triangle>
			<Triangle>33</Triangle>
			<Triangle>34</Triangle>
			<Triangle>35</Triangle>
			<Triangle>33</Triangle>
			<Triangle>36</Triangle>
			<Triangle>34</Triangle>
			<Triangle>36</Triangle>
			<Triangle>37</Triangle>
			<Triangle>34</Triangle>
			<Triangle>41</Triangle>
			<Triangle>34</Triangle>
			<Triangle>37</Triangle>
			<Triangle>41</Triangle>
			<Triangle>42</Triangle>
			<Triangle>34</Triangle>
			<Triangle>36</Triangle>
			<Triangle>38</Triangle>
			<Triangle>37</Triangle>
			<Triangle>39</Triangle>
			<Triangle>37</Triangle>
			<Triangle>38</Triangle>
			<Triangle>39</Triangle>
			<Triangle>40</Triangle>
			<Triangle>37</Triangle>
			<Triangle>40</Triangle>
			<Triangle>41</Triangle>
			<Triangle>37</Triangle>
			<Triangle>32</Triangle>
			<Triangle>25</Triangle>
			<Triangle>24</Triangle>
			<Triangle>23</Triangle>
			<Triangle>24</Triangle>
			<Triangle>25</Triangle>
			<Triangle>23</Triangle>
			<Triangle>26</Triangle>
			<Triangle>24</Triangle>
			<Triangle>26</Triangle>
			<Triangle>27</Triangle>
			<Triangle>24</Triangle>
			<Triangle>31</Triangle>
			<Triangle>24</Triangle>
			<Triangle>27</Triangle>
			<Triangle>31</Triangle>
			<Triangle>32</Triangle>
			<Triangle>24</Triangle>
			<Triangle>26</Triangle>
			<Triangle>28</Triangle>
			<Triangle>27</Triangle>
			<Triangle>29</Triangle>
			<Triangle>27</Triangle>
			<Triangle>28</Triangle>
			<Triangle>29</Triangle>
			<Triangle>30</Triangle>
			<Triangle>27</Triangle>
			<Triangle>30</Triangle>
			<Triangle>31</Triangle>
			<Triangle>27</Triangle>
			<Triangle>22</Triangle>
			<Triangle>15</Triangle>
			<Triangle>14</Triangle>
			<Triangle>13</Triangle>
			<Triangle>14</Triangle>
			<Triangle>15</Triangle>
			<Triangle>13</Triangle>
			<Triangle>16</Triangle>
			<Triangle>14</Triangle>
			<Triangle>16</Triangle>
			<Triangle>17</Triangle>
			<Triangle>14</Triangle>
			<Triangle>21</Triangle>
			<Triangle>14</Triangle>
			<Triangle>17</Triangle>
			<Triangle>21</Triangle>
			<Triangle>22</Triangle>
			<Triangle>14</Triangle>
			<Triangle>16</Triangle>
			<Triangle>18</Triangle>
			<Triangle>17</Triangle>
			<Triangle>19</Triangle>
			<Triangle>17</Triangle>
			<Triangle>18</Triangle>
			<Triangle>19</Triangle>
			<Triangle>20</Triangle>
			<Triangle>17</Triangle>
			<Triangle>20</Triangle>
			<Triangle>21</Triangle>
			<Triangle>17</Triangle>
			<Triangle>4</Triangle>
			<Triangle>3</Triangle>
			<Triangle>12</Triangle>
			<Triangle>3</Triangle>
			<Triangle>4</Triangle>
			<Triangle>5</Triangle>
			<Triangle>4</Triangle>
			<Triangle>6</Triangle>
			<Triangle>5</Triangle>
			<Triangle>4</Triangle>
			<Triangle>7</Triangle>
			<Triangle>6</Triangle>
			<Triangle>7</Triangle>
			<Triangle>8</Triangle>
			<Triangle>6</Triangle>
			<Triangle>8</Triangle>
			<Triangle>7</Triangle>
			<Triangle>9</Triangle>
			<Triangle>7</Triangle>
			<Triangle>10</Triangle>
			<Triangle>9</Triangle>
			<Triangle>4</Triangle>
			<Triangle>12</Triangle>
			<Triangle>11</Triangle>
			<Triangle>7</Triangle>
			<Triangle>4</Triangle>
			<Triangle>11</Triangle>
			<Triangle>7</Triangle>
			<Triangle>11</Triangle>
			<Triangle>10</Triangle>
		</Triangles>
		<Geosets>
			<Geoset triangle="0" triangles="318" />
		</Geosets>
		<Textures>
			<Texture geoset="0" color="-1" blend="0" texture="0" />
		</Textures>
	</View>
	<Colors />
	<Textures>
		<Texture type="2" file="" />
	</Textures>
	<Blending>
		<Blend>0</Blend>
	</Blending>
	<Attachments />
</Model>