<?xml version="1.0" encoding="utf-8"?>
<Model xmlns:xsi="http://www.w3.org/2001/XMLSchema-instance" xmlns:xsd="http://www.w3.org/2001/XMLSchema">
	<Name>Helm_Leather_A_02_GnM</Name>
	<Bones>
		<Bone>
			<Billboard>0</Billboard>
			<Parent>-1</Parent>
			<Translation x="0" y="0" z="0" />
			<Rotation x="0" y="0" z="-0" w="1" />
			<Scale x="1" y="1" z="1" />
			<Position x="0.008344328" y="-0.04279503" z="0.1074096" />
		</Bone>
	</Bones>
	<Vertices>
		<Vertex>
			<Position x="0.03124744" y="-0.2494378" z="0.1297561" />
			<Bones>
				<Bone index="0" weight="255" />
				<Bone index="0" weight="0" />
				<Bone index="0" weight="0" />
				<Bone index="0" weight="0" />
			</Bones>
			<Normal x="0.27628" y="-0.9453309" z="0.1732593" />
			<Texture x="0.5873016" y="0.984127" />
		</Vertex>
		<Vertex>
			<Position x="0.0974893" y="-0.1978276" z="0.1050263" />
			<Bones>
				<Bone index="0" weight="255" />
				<Bone index="0" weight="0" />
				<Bone index="0" weight="0" />
				<Bone index="0" weight="0" />
			</Bones>
			<Normal x="0.209179" y="-0.9590323" z="0.191053" />
			<Texture x="0.3968254" y="0.984127" />
		</Vertex>
		<Vertex>
			<Position x="0.05107846" y="-0.1571696" z="0.1070495" />
			<Bones>
				<Bone index="0" weight="255" />
				<Bone index="0" weight="0" />
				<Bone index="0" weight="0" />
				<Bone index="0" weight="0" />
			</Bones>
			<Normal x="0.3695297" y="-0.9274327" z="0.05758757" />
			<Texture x="0.3968254" y="0.7301587" />
		</Vertex>
		<Vertex>
			<Position x="0.03257735" y="-0.06673983" z="0.09156878" />
			<Bones>
				<Bone index="0" weight="255" />
				<Bone index="0" weight="0" />
				<Bone index="0" weight="0" />
				<Bone index="0" weight="0" />
			</Bones>
			<Normal x="0.7743114" y="-0.627418" z="0.08239221" />
			<Texture x="0.984127" y="0.8730159" />
		</Vertex>
		<Vertex>
			<Position x="0.009609872" y="-0.03858847" z="0.1162166" />
			<Bones>
				<Bone index="0" weight="255" />
				<Bone index="0" weight="0" />
				<Bone index="0" weight="0" />
				<Bone index="0" weight="0" />
			</Bones>
			<Normal x="0.7019359" y="-0.7101241" z="0.05486127" />
			<Texture x="0.984127" y="0.6507937" />
		</Vertex>
		<Vertex>
			<Position x="0.02712178" y="-0.07316246" z="0.09444938" />
			<Bones>
				<Bone index="0" weight="255" />
				<Bone index="0" weight="0" />
				<Bone index="0" weight="0" />
				<Bone index="0" weight="0" />
			</Bones>
			<Normal x="0.5844065" y="-0.7866209" z="-0.1992401" />
			<Texture x="0.968254" y="0.8730159" />
		</Vertex>
		<Vertex>
			<Position x="-0.002390936" y="-0.05089001" z="0.121102" />
			<Bones>
				<Bone index="0" weight="255" />
				<Bone index="0" weight="0" />
				<Bone index="0" weight="0" />
				<Bone index="0" weight="0" />
			</Bones>
			<Normal x="0.4836721" y="-0.8675228" z="-0.1160408" />
			<Texture x="0.9047619" y="0.6507937" />
		</Vertex>
		<Vertex>
			<Position x="-0.03861682" y="0.01788889" z="0.1438347" />
			<Bones>
				<Bone index="0" weight="255" />
				<Bone index="0" weight="0" />
				<Bone index="0" weight="0" />
				<Bone index="0" weight="0" />
			</Bones>
			<Normal x="0.5086155" y="-0.8478554" z="0.1498384" />
			<Texture x="0.984127" y="0.2698413" />
		</Vertex>
		<Vertex>
			<Position x="-0.04745966" y="0.008423833" z="0.1477528" />
			<Bones>
				<Bone index="0" weight="255" />
				<Bone index="0" weight="0" />
				<Bone index="0" weight="0" />
				<Bone index="0" weight="0" />
			</Bones>
			<Normal x="0.3533056" y="-0.9338022" z="0.05646829" />
			<Texture x="0.9047619" y="0.2857143" />
		</Vertex>
		<Vertex>
			<Position x="-0.09350787" y="0.07892589" z="0.1472334" />
			<Bones>
				<Bone index="0" weight="255" />
				<Bone index="0" weight="0" />
				<Bone index="0" weight="0" />
				<Bone index="0" weight="0" />
			</Bones>
			<Normal x="0.3472975" y="-0.9003548" z="0.262194" />
			<Texture x="0.968254" y="0.01587301" />
		</Vertex>
		<Vertex>
			<Position x="-0.03357815" y="0.03078829" z="0.1356385" />
			<Bones>
				<Bone index="0" weight="255" />
				<Bone index="0" weight="0" />
				<Bone index="0" weight="0" />
				<Bone index="0" weight="0" />
			</Bones>
			<Normal x="0.5653303" y="-0.7781619" z="0.273616" />
			<Texture x="0.9047619" y="0.2857143" />
		</Vertex>
		<Vertex>
			<Position x="0.01305238" y="-0.02395708" z="0.1059942" />
			<Bones>
				<Bone index="0" weight="255" />
				<Bone index="0" weight="0" />
				<Bone index="0" weight="0" />
				<Bone index="0" weight="0" />
			</Bones>
			<Normal x="0.746639" y="-0.6298622" z="0.2140182" />
			<Texture x="0.9047619" y="0.6507937" />
		</Vertex>
		<Vertex>
			<Position x="0.03256177" y="-0.05838015" z="0.08492062" />
			<Bones>
				<Bone index="0" weight="255" />
				<Bone index="0" weight="0" />
				<Bone index="0" weight="0" />
				<Bone index="0" weight="0" />
			</Bones>
			<Normal x="0.8492735" y="-0.4664739" z="0.2472581" />
			<Texture x="0.968254" y="0.8730159" />
		</Vertex>
		<Vertex>
			<Position x="0.03404064" y="-0.05485978" z="-0.1002606" />
			<Bones>
				<Bone index="0" weight="255" />
				<Bone index="0" weight="0" />
				<Bone index="0" weight="0" />
				<Bone index="0" weight="0" />
			</Bones>
			<Normal x="0.7145106" y="0.6983919" z="-0.04151387" />
			<Texture x="0.8412699" y="1" />
		</Vertex>
		<Vertex>
			<Position x="0.0084061" y="-0.02702833" z="-0.1281412" />
			<Bones>
				<Bone index="0" weight="255" />
				<Bone index="0" weight="0" />
				<Bone index="0" weight="0" />
				<Bone index="0" weight="0" />
			</Bones>
			<Normal x="0.7397987" y="0.6267858" z="0.2446169" />
			<Texture x="0.8253968" y="0.6507937" />
		</Vertex>
		<Vertex>
			<Position x="0.03692902" y="-0.04682137" z="-0.09724095" />
			<Bones>
				<Bone index="0" weight="255" />
				<Bone index="0" weight="0" />
				<Bone index="0" weight="0" />
				<Bone index="0" weight="0" />
			</Bones>
			<Normal x="0.7888895" y="0.5382843" z="0.2964849" />
			<Texture x="0.8571429" y="1" />
		</Vertex>
		<Vertex>
			<Position x="0.001286947" y="-0.04286603" z="-0.1333935" />
			<Bones>
				<Bone index="0" weight="255" />
				<Bone index="0" weight="0" />
				<Bone index="0" weight="0" />
				<Bone index="0" weight="0" />
			</Bones>
			<Normal x="0.6035025" y="0.7973572" z="0.002501015" />
			<Texture x="0.7460318" y="0.6507937" />
		</Vertex>
		<Vertex>
			<Position x="-0.05353018" y="0.01285111" z="-0.167021" />
			<Bones>
				<Bone index="0" weight="255" />
				<Bone index="0" weight="0" />
				<Bone index="0" weight="0" />
				<Bone index="0" weight="0" />
			</Bones>
			<Normal x="0.5453389" y="0.7931615" z="0.2711093" />
			<Texture x="0.8253968" y="0.2698413" />
		</Vertex>
		<Vertex>
			<Position x="-0.05860805" y="0.0007764493" z="-0.1711961" />
			<Bones>
				<Bone index="0" weight="255" />
				<Bone index="0" weight="0" />
				<Bone index="0" weight="0" />
				<Bone index="0" weight="0" />
			</Bones>
			<Normal x="0.4339519" y="0.8920866" z="0.1259654" />
			<Texture x="0.7460318" y="0.2857143" />
		</Vertex>
		<Vertex>
			<Position x="-0.12634" y="0.05610686" z="-0.1810531" />
			<Bones>
				<Bone index="0" weight="255" />
				<Bone index="0" weight="0" />
				<Bone index="0" weight="0" />
				<Bone index="0" weight="0" />
			</Bones>
			<Normal x="0.3626928" y="0.8724787" z="0.3274673" />
			<Texture x="0.8095238" y="0.01587301" />
		</Vertex>
		<Vertex>
			<Position x="-0.05378248" y="0.02731194" z="-0.1589291" />
			<Bones>
				<Bone index="0" weight="255" />
				<Bone index="0" weight="0" />
				<Bone index="0" weight="0" />
				<Bone index="0" weight="0" />
			</Bones>
			<Normal x="0.5538123" y="0.7224627" z="0.4139318" />
			<Texture x="0.7460318" y="0.2857143" />
		</Vertex>
		<Vertex>
			<Position x="0.005795387" y="-0.01127241" z="-0.1181844" />
			<Bones>
				<Bone index="0" weight="255" />
				<Bone index="0" weight="0" />
				<Bone index="0" weight="0" />
				<Bone index="0" weight="0" />
			</Bones>
			<Normal x="0.7234243" y="0.5495009" z="0.4179786" />
			<Texture x="0.7460318" y="0.6507937" />
		</Vertex>
		<Vertex>
			<Position x="0.0334097" y="-0.03838318" z="-0.09087314" />
			<Bones>
				<Bone index="0" weight="255" />
				<Bone index="0" weight="0" />
				<Bone index="0" weight="0" />
				<Bone index="0" weight="0" />
			</Bones>
			<Normal x="0.7869661" y="0.3798469" z="0.4862106" />
			<Texture x="0.8412699" y="1" />
		</Vertex>
		<Vertex>
			<Position x="0.05820998" y="-0.07041909" z="-0.08212145" />
			<Bones>
				<Bone index="0" weight="255" />
				<Bone index="0" weight="0" />
				<Bone index="0" weight="0" />
				<Bone index="0" weight="0" />
			</Bones>
			<Normal x="0.6680567" y="0.7441087" z="0.00157087" />
			<Texture x="0.968254" y="0.8730159" />
		</Vertex>
		<Vertex>
			<Position x="0.02011365" y="-0.04928578" z="-0.1162795" />
			<Bones>
				<Bone index="0" weight="255" />
				<Bone index="0" weight="0" />
				<Bone index="0" weight="0" />
				<Bone index="0" weight="0" />
			</Bones>
			<Normal x="0.6390381" y="0.7119958" z="0.2910194" />
			<Texture x="0.984127" y="0.6507937" />
		</Vertex>
		<Vertex>
			<Position x="0.05946375" y="-0.06026595" z="-0.08038918" />
			<Bones>
				<Bone index="0" weight="255" />
				<Bone index="0" weight="0" />
				<Bone index="0" weight="0" />
				<Bone index="0" weight="0" />
			</Bones>
			<Normal x="0.6809695" y="0.6350393" z="0.3646993" />
			<Texture x="0.984127" y="0.8730159" />
		</Vertex>
		<Vertex>
			<Position x="0.01614473" y="-0.06949051" z="-0.1187119" />
			<Bones>
				<Bone index="0" weight="255" />
				<Bone index="0" weight="0" />
				<Bone index="0" weight="0" />
				<Bone index="0" weight="0" />
			</Bones>
			<Normal x="0.5450598" y="0.8383938" z="0.00236221" />
			<Texture x="0.9047619" y="0.6507937" />
		</Vertex>
		<Vertex>
			<Position x="-0.06193779" y="-0.02435979" z="-0.1609454" />
			<Bones>
				<Bone index="0" weight="255" />
				<Bone index="0" weight="0" />
				<Bone index="0" weight="0" />
				<Bone index="0" weight="0" />
			</Bones>
			<Normal x="0.4339964" y="0.865747" z="0.2492573" />
			<Texture x="0.984127" y="0.2698413" />
		</Vertex>
		<Vertex>
			<Position x="-0.06459669" y="-0.03971479" z="-0.1630399" />
			<Bones>
				<Bone index="0" weight="255" />
				<Bone index="0" weight="0" />
				<Bone index="0" weight="0" />
				<Bone index="0" weight="0" />
			</Bones>
			<Normal x="0.3459838" y="0.935792" z="0.06773956" />
			<Texture x="0.9047619" y="0.2857143" />
		</Vertex>
		<Vertex>
			<Position x="-0.1545435" y="0.005994809" z="-0.1760856" />
			<Bones>
				<Bone index="0" weight="255" />
				<Bone index="0" weight="0" />
				<Bone index="0" weight="0" />
				<Bone index="0" weight="0" />
			</Bones>
			<Normal x="0.236016" y="0.9385274" z="0.2519182" />
			<Texture x="0.968254" y="0.01587301" />
		</Vertex>
		<Vertex>
			<Position x="-0.06539903" y="-0.006859433" z="-0.1540885" />
			<Bones>
				<Bone index="0" weight="255" />
				<Bone index="0" weight="0" />
				<Bone index="0" weight="0" />
				<Bone index="0" weight="0" />
			</Bones>
			<Normal x="0.4179382" y="0.8147467" z="0.4018899" />
			<Texture x="0.9047619" y="0.2857143" />
		</Vertex>
		<Vertex>
			<Position x="0.01389154" y="-0.03054601" z="-0.1072049" />
			<Bones>
				<Bone index="0" weight="255" />
				<Bone index="0" weight="0" />
				<Bone index="0" weight="0" />
				<Bone index="0" weight="0" />
			</Bones>
			<Normal x="0.5929973" y="0.6560073" z="0.4669139" />
			<Texture x="0.9047619" y="0.6507937" />
		</Vertex>
		<Vertex>
			<Position x="0.05390589" y="-0.05052748" z="-0.07407291" />
			<Bones>
				<Bone index="0" weight="255" />
				<Bone index="0" weight="0" />
				<Bone index="0" weight="0" />
				<Bone index="0" weight="0" />
			</Bones>
			<Normal x="0.64941" y="0.5031693" z="0.5701643" />
			<Texture x="0.968254" y="0.8730159" />
		</Vertex>
		<Vertex>
			<Position x="0.06194475" y="-0.1835097" z="-0.1063251" />
			<Bones>
				<Bone index="0" weight="255" />
				<Bone index="0" weight="0" />
				<Bone index="0" weight="0" />
				<Bone index="0" weight="0" />
			</Bones>
			<Normal x="0.6623422" y="0.703261" z="0.2583151" />
			<Texture x="0.968254" y="0.8730159" />
		</Vertex>
		<Vertex>
			<Position x="0.06822173" y="-0.2276896" z="-0.116641" />
			<Bones>
				<Bone index="0" weight="255" />
				<Bone index="0" weight="0" />
				<Bone index="0" weight="0" />
				<Bone index="0" weight="0" />
			</Bones>
			<Normal x="0.4520843" y="0.8784674" z="0.1546439" />
			<Texture x="0.984127" y="0.6507937" />
		</Vertex>
		<Vertex>
			<Position x="0.0557215" y="-0.1847096" z="-0.1121147" />
			<Bones>
				<Bone index="0" weight="255" />
				<Bone index="0" weight="0" />
				<Bone index="0" weight="0" />
				<Bone index="0" weight="0" />
			</Bones>
			<Normal x="0.3527586" y="0.9143332" z="0.198887" />
			<Texture x="0.984127" y="0.8730159" />
		</Vertex>
		<Vertex>
			<Position x="0.0797925" y="-0.2259903" z="-0.104092" />
			<Bones>
				<Bone index="0" weight="255" />
				<Bone index="0" weight="0" />
				<Bone index="0" weight="0" />
				<Bone index="0" weight="0" />
			</Bones>
			<Normal x="0.7168964" y="0.6877823" z="0.1140834" />
			<Texture x="0.9047619" y="0.6507937" />
		</Vertex>
		<Vertex>
			<Position x="0.07411089" y="-0.3074495" z="-0.1150519" />
			<Bones>
				<Bone index="0" weight="255" />
				<Bone index="0" weight="0" />
				<Bone index="0" weight="0" />
				<Bone index="0" weight="0" />
			</Bones>
			<Normal x="0.5674329" y="0.8203852" z="-0.07062615" />
			<Texture x="0.984127" y="0.2698413" />
		</Vertex>
		<Vertex>
			<Position x="0.08310156" y="-0.3059912" z="-0.1057641" />
			<Bones>
				<Bone index="0" weight="255" />
				<Bone index="0" weight="0" />
				<Bone index="0" weight="0" />
				<Bone index="0" weight="0" />
			</Bones>
			<Normal x="0.7226875" y="0.6812315" z="-0.1168179" />
			<Texture x="0.9047619" y="0.2857143" />
		</Vertex>
		<Vertex>
			<Position x="0.05725016" y="-0.3859021" z="-0.1002781" />
			<Bones>
				<Bone index="0" weight="255" />
				<Bone index="0" weight="0" />
				<Bone index="0" weight="0" />
				<Bone index="0" weight="0" />
			</Bones>
			<Normal x="0.5938677" y="0.7577869" z="-0.2703335" />
			<Texture x="0.968254" y="0.01587301" />
		</Vertex>
		<Vertex>
			<Position x="0.06028122" y="-0.3121437" z="-0.1211108" />
			<Bones>
				<Bone index="0" weight="255" />
				<Bone index="0" weight="0" />
				<Bone index="0" weight="0" />
				<Bone index="0" weight="0" />
			</Bones>
			<Normal x="0.4303561" y="0.8957152" z="-0.1117496" />
			<Texture x="0.9047619" y="0.2857143" />
		</Vertex>
		<Vertex>
			<Position x="0.05202414" y="-0.2338911" z="-0.121375" />
			<Bones>
				<Bone index="0" weight="255" />
				<Bone index="0" weight="0" />
				<Bone index="0" weight="0" />
				<Bone index="0" weight="0" />
			</Bones>
			<Normal x="0.2924049" y="0.9527161" z="0.0826523" />
			<Texture x="0.9047619" y="0.6507937" />
		</Vertex>
		<Vertex>
			<Position x="0.04602123" y="-0.189018" z="-0.112954" />
			<Bones>
				<Bone index="0" weight="255" />
				<Bone index="0" weight="0" />
				<Bone index="0" weight="0" />
				<Bone index="0" weight="0" />
			</Bones>
			<Normal x="0.1184198" y="0.9797595" z="0.1613942" />
			<Texture x="0.968254" y="0.8730159" />
		</Vertex>
		<Vertex>
			<Position x="0.07296313" y="-0.1951026" z="0.1091047" />
			<Bones>
				<Bone index="0" weight="255" />
				<Bone index="0" weight="0" />
				<Bone index="0" weight="0" />
				<Bone index="0" weight="0" />
			</Bones>
			<Normal x="0.3780333" y="-0.9150228" z="0.1407984" />
			<Texture x="0.8571429" y="1" />
		</Vertex>
		<Vertex>
			<Position x="0.07911338" y="-0.2352177" z="0.1127365" />
			<Bones>
				<Bone index="0" weight="255" />
				<Bone index="0" weight="0" />
				<Bone index="0" weight="0" />
				<Bone index="0" weight="0" />
			</Bones>
			<Normal x="0.4695732" y="-0.8785383" z="0.08758743" />
			<Texture x="0.8253968" y="0.6507937" />
		</Vertex>
		<Vertex>
			<Position x="0.07869934" y="-0.1947605" z="0.1038554" />
			<Bones>
				<Bone index="0" weight="255" />
				<Bone index="0" weight="0" />
				<Bone index="0" weight="0" />
				<Bone index="0" weight="0" />
			</Bones>
			<Normal x="0.6914978" y="-0.704064" z="0.1616315" />
			<Texture x="0.8412699" y="1" />
		</Vertex>
		<Vertex>
			<Position x="0.0897157" y="-0.2350595" z="0.1013585" />
			<Bones>
				<Bone index="0" weight="255" />
				<Bone index="0" weight="0" />
				<Bone index="0" weight="0" />
				<Bone index="0" weight="0" />
			</Bones>
			<Normal x="0.7257093" y="-0.6877925" z="0.01695283" />
			<Texture x="0.7460318" y="0.6507937" />
		</Vertex>
		<Vertex>
			<Position x="0.07496803" y="-0.3076127" z="0.1112956" />
			<Bones>
				<Bone index="0" weight="255" />
				<Bone index="0" weight="0" />
				<Bone index="0" weight="0" />
				<Bone index="0" weight="0" />
			</Bones>
			<Normal x="0.5533607" y="-0.8203845" z="-0.1440874" />
			<Texture x="0.8253968" y="0.2698413" />
		</Vertex>
		<Vertex>
			<Position x="0.08322254" y="-0.3073658" z="0.1028746" />
			<Bones>
				<Bone index="0" weight="255" />
				<Bone index="0" weight="0" />
				<Bone index="0" weight="0" />
				<Bone index="0" weight="0" />
			</Bones>
			<Normal x="0.7012574" y="-0.681231" z="-0.2101488" />
			<Texture x="0.7460318" y="0.2857143" />
		</Vertex>
		<Vertex>
			<Position x="0.05052704" y="-0.3761402" z="0.0979005" />
			<Bones>
				<Bone index="0" weight="255" />
				<Bone index="0" weight="0" />
				<Bone index="0" weight="0" />
				<Bone index="0" weight="0" />
			</Bones>
			<Normal x="0.553502" y="-0.7577862" z="-0.3455366" />
			<Texture x="0.8095238" y="0.01587301" />
		</Vertex>
		<Vertex>
			<Position x="0.06198071" y="-0.3101957" z="0.1167891" />
			<Bones>
				<Bone index="0" weight="255" />
				<Bone index="0" weight="0" />
				<Bone index="0" weight="0" />
				<Bone index="0" weight="0" />
			</Bones>
			<Normal x="0.412089" y="-0.8957146" z="-0.1669669" />
			<Texture x="0.7460318" y="0.2857143" />
		</Vertex>
		<Vertex>
			<Position x="0.06381908" y="-0.2388755" z="0.1170287" />
			<Bones>
				<Bone index="0" weight="255" />
				<Bone index="0" weight="0" />
				<Bone index="0" weight="0" />
				<Bone index="0" weight="0" />
			</Bones>
			<Normal x="0.3015124" y="-0.9526172" z="0.04013337" />
			<Texture x="0.7460318" y="0.6507937" />
		</Vertex>
		<Vertex>
			<Position x="0.06373346" y="-0.1978276" z="0.1098657" />
			<Bones>
				<Bone index="0" weight="255" />
				<Bone index="0" weight="0" />
				<Bone index="0" weight="0" />
				<Bone index="0" weight="0" />
			</Bones>
			<Normal x="0.1416284" y="-0.9808677" z="0.1335663" />
			<Texture x="0.8412699" y="1" />
		</Vertex>
		<Vertex>
			<Position x="0.06257185" y="-0.2108897" z="-0.1127039" />
			<Bones>
				<Bone index="0" weight="255" />
				<Bone index="0" weight="0" />
				<Bone index="0" weight="0" />
				<Bone index="0" weight="0" />
			</Bones>
			<Normal x="0.6608396" y="0.6737676" z="0.3306484" />
			<Texture x="0.8412699" y="1" />
		</Vertex>
		<Vertex>
			<Position x="0.06283328" y="-0.2458972" z="-0.1296273" />
			<Bones>
				<Bone index="0" weight="255" />
				<Bone index="0" weight="0" />
				<Bone index="0" weight="0" />
				<Bone index="0" weight="0" />
			</Bones>
			<Normal x="0.429994" y="0.854745" z="0.2907165" />
			<Texture x="0.8253968" y="0.6507937" />
		</Vertex>
		<Vertex>
			<Position x="0.05681923" y="-0.2099365" z="-0.1174132" />
			<Bones>
				<Bone index="0" weight="255" />
				<Bone index="0" weight="0" />
				<Bone index="0" weight="0" />
				<Bone index="0" weight="0" />
			</Bones>
			<Normal x="0.3365095" y="0.8730853" z="0.3528219" />
			<Texture x="0.8571429" y="1" />
		</Vertex>
		<Vertex>
			<Position x="0.07356045" y="-0.248541" z="-0.1194688" />
			<Bones>
				<Bone index="0" weight="255" />
				<Bone index="0" weight="0" />
				<Bone index="0" weight="0" />
				<Bone index="0" weight="0" />
			</Bones>
			<Normal x="0.6935345" y="0.6973457" z="0.1808836" />
			<Texture x="0.7460318" y="0.6507937" />
		</Vertex>
		<Vertex>
			<Position x="0.05961757" y="-0.3134428" z="-0.1428981" />
			<Bones>
				<Bone index="0" weight="255" />
				<Bone index="0" weight="0" />
				<Bone index="0" weight="0" />
				<Bone index="0" weight="0" />
			</Bones>
			<Normal x="0.5136678" y="0.8566776" z="0.04742186" />
			<Texture x="0.8253968" y="0.2698413" />
		</Vertex>
		<Vertex>
			<Position x="0.06794459" y="-0.3152709" z="-0.1353688" />
			<Bones>
				<Bone index="0" weight="255" />
				<Bone index="0" weight="0" />
				<Bone index="0" weight="0" />
				<Bone index="0" weight="0" />
			</Bones>
			<Normal x="0.6649596" y="0.7456804" z="-0.04230145" />
			<Texture x="0.7460318" y="0.2857143" />
		</Vertex>
		<Vertex>
			<Position x="0.03764513" y="-0.3809761" z="-0.1435394" />
			<Bones>
				<Bone index="0" weight="255" />
				<Bone index="0" weight="0" />
				<Bone index="0" weight="0" />
				<Bone index="0" weight="0" />
			</Bones>
			<Normal x="0.5135614" y="0.8431767" z="-0.1590839" />
			<Texture x="0.8095238" y="0.01587301" />
		</Vertex>
		<Vertex>
			<Position x="0.04695373" y="-0.314649" z="-0.1480132" />
			<Bones>
				<Bone index="0" weight="255" />
				<Bone index="0" weight="0" />
				<Bone index="0" weight="0" />
				<Bone index="0" weight="0" />
			</Bones>
			<Normal x="0.3710831" y="0.9278005" z="0.03851681" />
			<Texture x="0.7460318" y="0.2857143" />
		</Vertex>
		<Vertex>
			<Position x="0.04804277" y="-0.2484637" z="-0.1337614" />
			<Bones>
				<Bone index="0" weight="255" />
				<Bone index="0" weight="0" />
				<Bone index="0" weight="0" />
				<Bone index="0" weight="0" />
			</Bones>
			<Normal x="0.2597331" y="0.9317705" z="0.2536581" />
			<Texture x="0.7460318" y="0.6507937" />
		</Vertex>
		<Vertex>
			<Position x="0.04799678" y="-0.2124481" z="-0.1183204" />
			<Bones>
				<Bone index="0" weight="255" />
				<Bone index="0" weight="0" />
				<Bone index="0" weight="0" />
				<Bone index="0" weight="0" />
			</Bones>
			<Normal x="0.09583317" y="0.9293118" z="0.356645" />
			<Texture x="0.8412699" y="1" />
		</Vertex>
		<Vertex>
			<Position x="0.03719439" y="-0.05797634" z="0.09175058" />
			<Bones>
				<Bone index="0" weight="255" />
				<Bone index="0" weight="0" />
				<Bone index="0" weight="0" />
				<Bone index="0" weight="0" />
			</Bones>
			<Normal x="0.5930532" y="-0.7980408" z="0.106859" />
			<Texture x="0.8571429" y="1" />
		</Vertex>
		<Vertex>
			<Position x="-0.006844969" y="-0.04448749" z="0.1226716" />
			<Bones>
				<Bone index="0" weight="255" />
				<Bone index="0" weight="0" />
				<Bone index="0" weight="0" />
				<Bone index="0" weight="0" />
			</Bones>
			<Normal x="0.5743943" y="-0.7917113" z="0.2080012" />
			<Texture x="0.8253968" y="0.6507937" />
		</Vertex>
		<Vertex>
			<Position x="0.0337606" y="-0.06797497" z="0.09122257" />
			<Bones>
				<Bone index="0" weight="255" />
				<Bone index="0" weight="0" />
				<Bone index="0" weight="0" />
				<Bone index="0" weight="0" />
			</Bones>
			<Normal x="0.6308354" y="-0.7740209" z="0.054207" />
			<Texture x="0.8412699" y="1" />
		</Vertex>
		<Vertex>
			<Position x="0.01400568" y="-0.08426154" z="0.1203708" />
			<Bones>
				<Bone index="0" weight="255" />
				<Bone index="0" weight="0" />
				<Bone index="0" weight="0" />
				<Bone index="0" weight="0" />
			</Bones>
			<Normal x="0.4705696" y="-0.8749782" z="0.1139183" />
			<Texture x="0.7460318" y="0.6507937" />
		</Vertex>
		<Vertex>
			<Position x="-0.0921087" y="-0.00948015" z="0.1578006" />
			<Bones>
				<Bone index="0" weight="255" />
				<Bone index="0" weight="0" />
				<Bone index="0" weight="0" />
				<Bone index="0" weight="0" />
			</Bones>
			<Normal x="0.2970869" y="-0.950902" z="0.08674591" />
			<Texture x="0.8253968" y="0.2698413" />
		</Vertex>
		<Vertex>
			<Position x="-0.0979434" y="-0.02435181" z="0.1563551" />
			<Bones>
				<Bone index="0" weight="255" />
				<Bone index="0" weight="0" />
				<Bone index="0" weight="0" />
				<Bone index="0" weight="0" />
			</Bones>
			<Normal x="0.1109135" y="-0.9840387" z="-0.1391624" />
			<Texture x="0.7460318" y="0.2857143" />
		</Vertex>
		<Vertex>
			<Position x="-0.1806922" y="0.03792515" z="0.1631113" />
			<Bones>
				<Bone index="0" weight="255" />
				<Bone index="0" weight="0" />
				<Bone index="0" weight="0" />
				<Bone index="0" weight="0" />
			</Bones>
			<Normal x="0.08328779" y="-0.9955491" z="0.04410468" />
			<Texture x="0.8095238" y="0.01587301" />
		</Vertex>
		<Vertex>
			<Position x="-0.09091947" y="0.009594181" z="0.1539421" />
			<Bones>
				<Bone index="0" weight="255" />
				<Bone index="0" weight="0" />
				<Bone index="0" weight="0" />
				<Bone index="0" weight="0" />
			</Bones>
			<Normal x="0.3101596" y="-0.9353839" z="0.1698763" />
			<Texture x="0.7460318" y="0.2857143" />
		</Vertex>
		<Vertex>
			<Position x="-0.007687681" y="-0.02323881" z="0.1164062" />
			<Bones>
				<Bone index="0" weight="255" />
				<Bone index="0" weight="0" />
				<Bone index="0" weight="0" />
				<Bone index="0" weight="0" />
			</Bones>
			<Normal x="0.5223178" y="-0.8236903" z="0.2207225" />
			<Texture x="0.7460318" y="0.6507937" />
		</Vertex>
		<Vertex>
			<Position x="0.03480117" y="-0.04617323" z="0.08652314" />
			<Bones>
				<Bone index="0" weight="255" />
				<Bone index="0" weight="0" />
				<Bone index="0" weight="0" />
				<Bone index="0" weight="0" />
			</Bones>
			<Normal x="0.6258239" y="-0.7054908" z="0.3326067" />
			<Texture x="0.8412699" y="1" />
		</Vertex>
		<Vertex>
			<Position x="0.07813673" y="-0.1958992" z="0.1040388" />
			<Bones>
				<Bone index="0" weight="255" />
				<Bone index="0" weight="0" />
				<Bone index="0" weight="0" />
				<Bone index="0" weight="0" />
			</Bones>
			<Normal x="0.2890626" y="-0.8822041" z="0.3716972" />
			<Texture x="0.984127" y="0.8730159" />
		</Vertex>
		<Vertex>
			<Position x="0.07256661" y="-0.2243153" z="0.1178364" />
			<Bones>
				<Bone index="0" weight="255" />
				<Bone index="0" weight="0" />
				<Bone index="0" weight="0" />
				<Bone index="0" weight="0" />
			</Bones>
			<Normal x="0.3618568" y="-0.8863268" z="0.2889367" />
			<Texture x="0.984127" y="0.6507937" />
		</Vertex>
		<Vertex>
			<Position x="0.08327344" y="-0.198685" z="0.1010835" />
			<Bones>
				<Bone index="0" weight="255" />
				<Bone index="0" weight="0" />
				<Bone index="0" weight="0" />
				<Bone index="0" weight="0" />
			</Bones>
			<Normal x="0.6130033" y="-0.753809" z="0.2366409" />
			<Texture x="0.968254" y="0.8730159" />
		</Vertex>
		<Vertex>
			<Position x="0.08215209" y="-0.2304406" z="0.1112648" />
			<Bones>
				<Bone index="0" weight="255" />
				<Bone index="0" weight="0" />
				<Bone index="0" weight="0" />
				<Bone index="0" weight="0" />
			</Bones>
			<Normal x="0.5973309" y="-0.7960625" z="0.09736674" />
			<Texture x="0.9047619" y="0.6507937" />
		</Vertex>
		<Vertex>
			<Position x="0.05189975" y="-0.2761832" z="0.1344797" />
			<Bones>
				<Bone index="0" weight="255" />
				<Bone index="0" weight="0" />
				<Bone index="0" weight="0" />
				<Bone index="0" weight="0" />
			</Bones>
			<Normal x="0.3723452" y="-0.9270074" z="0.04490239" />
			<Texture x="0.984127" y="0.2698413" />
		</Vertex>
		<Vertex>
			<Position x="0.05933876" y="-0.2806972" z="0.1296529" />
			<Bones>
				<Bone index="0" weight="255" />
				<Bone index="0" weight="0" />
				<Bone index="0" weight="0" />
				<Bone index="0" weight="0" />
			</Bones>
			<Normal x="0.5015588" y="-0.8600963" z="-0.09312934" />
			<Texture x="0.9047619" y="0.2857143" />
		</Vertex>
		<Vertex>
			<Position x="0.01806657" y="-0.3261153" z="0.1378831" />
			<Bones>
				<Bone index="0" weight="255" />
				<Bone index="0" weight="0" />
				<Bone index="0" weight="0" />
				<Bone index="0" weight="0" />
			</Bones>
			<Normal x="0.3162778" y="-0.9366589" z="-0.1504608" />
			<Texture x="0.968254" y="0.01587301" />
		</Vertex>
		<Vertex>
			<Position x="0.04061777" y="-0.2735998" z="0.1369399" />
			<Bones>
				<Bone index="0" weight="255" />
				<Bone index="0" weight="0" />
				<Bone index="0" weight="0" />
				<Bone index="0" weight="0" />
			</Bones>
			<Normal x="0.2302618" y="-0.9696542" z="0.0821602" />
			<Texture x="0.9047619" y="0.2857143" />
		</Vertex>
		<Vertex>
			<Position x="0.05939914" y="-0.2225416" z="0.1192924" />
			<Bones>
				<Bone index="0" weight="255" />
				<Bone index="0" weight="0" />
				<Bone index="0" weight="0" />
				<Bone index="0" weight="0" />
			</Bones>
			<Normal x="0.1862247" y="-0.9314877" z="0.3124916" />
			<Texture x="0.9047619" y="0.6507937" />
		</Vertex>
		<Vertex>
			<Position x="0.07029013" y="-0.1958946" z="0.1037065" />
			<Bones>
				<Bone index="0" weight="255" />
				<Bone index="0" weight="0" />
				<Bone index="0" weight="0" />
				<Bone index="0" weight="0" />
			</Bones>
			<Normal x="0.06034495" y="-0.8918723" z="0.4482434" />
			<Texture x="0.968254" y="0.8730159" />
		</Vertex>
		<Vertex>
			<Position x="0.09783272" y="-0.1940356" z="-0.1096565" />
			<Bones>
				<Bone index="0" weight="255" />
				<Bone index="0" weight="0" />
				<Bone index="0" weight="0" />
				<Bone index="0" weight="0" />
			</Bones>
			<Normal x="0.1149889" y="0.9748632" z="0.1908383" />
			<Texture x="0.3968254" y="0.984127" />
		</Vertex>
		<Vertex>
			<Position x="0.03124741" y="-0.2494378" z="-0.128356" />
			<Bones>
				<Bone index="0" weight="255" />
				<Bone index="0" weight="0" />
				<Bone index="0" weight="0" />
				<Bone index="0" weight="0" />
			</Bones>
			<Normal x="0.1871311" y="0.9668796" z="0.1735677" />
			<Texture x="0.5873016" y="0.984127" />
		</Vertex>
		<Vertex>
			<Position x="0.05107842" y="-0.1571696" z="-0.1079545" />
			<Bones>
				<Bone index="0" weight="255" />
				<Bone index="0" weight="0" />
				<Bone index="0" weight="0" />
				<Bone index="0" weight="0" />
			</Bones>
			<Normal x="0.3330055" y="0.9426419" z="0.02309987" />
			<Texture x="0.3968254" y="0.7301587" />
		</Vertex>
		<Vertex>
			<Position x="-0.01679907" y="-0.1947496" z="-0.1324591" />
			<Bones>
				<Bone index="0" weight="255" />
				<Bone index="0" weight="0" />
				<Bone index="0" weight="0" />
				<Bone index="0" weight="0" />
			</Bones>
			<Normal x="0.3303694" y="0.9436681" z="0.01861484" />
			<Texture x="0.6507937" y="0.8888889" />
		</Vertex>
		<Vertex>
			<Position x="-0.03451337" y="-0.1518519" z="-0.1457113" />
			<Bones>
				<Bone index="0" weight="255" />
				<Bone index="0" weight="0" />
				<Bone index="0" weight="0" />
				<Bone index="0" weight="0" />
			</Bones>
			<Normal x="0.394799" y="0.9113688" z="-0.1163643" />
			<Texture x="0.6984127" y="0.7301587" />
		</Vertex>
		<Vertex>
			<Position x="-0.01814278" y="-0.09960689" z="-0.1451614" />
			<Bones>
				<Bone index="0" weight="255" />
				<Bone index="0" weight="0" />
				<Bone index="0" weight="0" />
				<Bone index="0" weight="0" />
			</Bones>
			<Normal x="0.4392296" y="0.8964315" z="0.05905891" />
			<Texture x="0.6984127" y="0.4920635" />
		</Vertex>
		<Vertex>
			<Position x="0.05203627" y="-0.09717967" z="-0.1074351" />
			<Bones>
				<Bone index="0" weight="255" />
				<Bone index="0" weight="0" />
				<Bone index="0" weight="0" />
				<Bone index="0" weight="0" />
			</Bones>
			<Normal x="0.4720597" y="0.8806788" z="0.03955315" />
			<Texture x="0.3968254" y="0.4920635" />
		</Vertex>
		<Vertex>
			<Position x="0.05876647" y="-0.07194505" z="-0.1015712" />
			<Bones>
				<Bone index="0" weight="255" />
				<Bone index="0" weight="0" />
				<Bone index="0" weight="0" />
				<Bone index="0" weight="0" />
			</Bones>
			<Normal x="0.416073" y="0.8887815" z="0.1922256" />
			<Texture x="0.3968254" y="0.3333333" />
		</Vertex>
		<Vertex>
			<Position x="0.1161715" y="-0.06554407" z="-0.07235601" />
			<Bones>
				<Bone index="0" weight="255" />
				<Bone index="0" weight="0" />
				<Bone index="0" weight="0" />
				<Bone index="0" weight="0" />
			</Bones>
			<Normal x="0.716333" y="0.6039739" z="0.3494033" />
			<Texture x="0.3174603" y="0.3333333" />
		</Vertex>
		<Vertex>
			<Position x="0.1619565" y="-0.06306578" z="0.0002027356" />
			<Bones>
				<Bone index="0" weight="255" />
				<Bone index="0" weight="0" />
				<Bone index="0" weight="0" />
				<Bone index="0" weight="0" />
			</Bones>
			<Normal x="0.9162382" y="-5.30198E-08" z="0.4006339" />
			<Texture x="0.02376723" y="0.3333333" />
		</Vertex>
		<Vertex>
			<Position x="0.1467854" y="-0.1001441" z="-0.06105705" />
			<Bones>
				<Bone index="0" weight="255" />
				<Bone index="0" weight="0" />
				<Bone index="0" weight="0" />
				<Bone index="0" weight="0" />
			</Bones>
			<Normal x="0.8371294" y="0.4196696" z="0.3508446" />
			<Texture x="0.3015873" y="0.6349206" />
		</Vertex>
		<Vertex>
			<Position x="0.1767367" y="-0.1307881" z="0.0002027285" />
			<Bones>
				<Bone index="0" weight="255" />
				<Bone index="0" weight="0" />
				<Bone index="0" weight="0" />
				<Bone index="0" weight="0" />
			</Bones>
			<Normal x="0.9770024" y="-2.748615E-08" z="0.2132285" />
			<Texture x="0.02376723" y="0.7460318" />
		</Vertex>
		<Vertex>
			<Position x="0.1467855" y="-0.1001441" z="0.0614625" />
			<Bones>
				<Bone index="0" weight="255" />
				<Bone index="0" weight="0" />
				<Bone index="0" weight="0" />
				<Bone index="0" weight="0" />
			</Bones>
			<Normal x="0.8371293" y="-0.4196697" z="0.3508445" />
			<Texture x="0.3015873" y="0.6349206" />
		</Vertex>
		<Vertex>
			<Position x="0.1161715" y="-0.06554409" z="0.07276146" />
			<Bones>
				<Bone index="0" weight="255" />
				<Bone index="0" weight="0" />
				<Bone index="0" weight="0" />
				<Bone index="0" weight="0" />
			</Bones>
			<Normal x="0.716333" y="-0.6039739" z="0.3494031" />
			<Texture x="0.3174603" y="0.3333333" />
		</Vertex>
		<Vertex>
			<Position x="0.1347816" y="-0.005925445" z="0.0002027422" />
			<Bones>
				<Bone index="0" weight="255" />
				<Bone index="0" weight="0" />
				<Bone index="0" weight="0" />
				<Bone index="0" weight="0" />
			</Bones>
			<Normal x="0.9208579" y="-6.758138E-09" z="0.3898984" />
			<Texture x="0.02376723" y="0.01587301" />
		</Vertex>
		<Vertex>
			<Position x="0.09813446" y="-0.01517682" z="-0.07091131" />
			<Bones>
				<Bone index="0" weight="255" />
				<Bone index="0" weight="0" />
				<Bone index="0" weight="0" />
				<Bone index="0" weight="0" />
			</Bones>
			<Normal x="0.5636957" y="0.785981" z="0.2539311" />
			<Texture x="0.3174603" y="0.01587301" />
		</Vertex>
		<Vertex>
			<Position x="0.0221454" y="-0.02040439" z="-0.1024702" />
			<Bones>
				<Bone index="0" weight="255" />
				<Bone index="0" weight="0" />
				<Bone index="0" weight="0" />
				<Bone index="0" weight="0" />
			</Bones>
			<Normal x="0.3793053" y="0.8897288" z="0.2539882" />
			<Texture x="0.6984127" y="0.01587301" />
		</Vertex>
		<Vertex>
			<Position x="0.09813447" y="-0.01517683" z="0.07131679" />
			<Bones>
				<Bone index="0" weight="255" />
				<Bone index="0" weight="0" />
				<Bone index="0" weight="0" />
				<Bone index="0" weight="0" />
			</Bones>
			<Normal x="0.5636958" y="-0.785981" z="0.2539307" />
			<Texture x="0.3174603" y="0.01587301" />
		</Vertex>
		<Vertex>
			<Position x="0.0587665" y="-0.07194506" z="0.1019766" />
			<Bones>
				<Bone index="0" weight="255" />
				<Bone index="0" weight="0" />
				<Bone index="0" weight="0" />
				<Bone index="0" weight="0" />
			</Bones>
			<Normal x="0.3978727" y="-0.8974835" z="0.190317" />
			<Texture x="0.3968254" y="0.3333333" />
		</Vertex>
		<Vertex>
			<Position x="0.02214543" y="-0.02040442" z="0.1028756" />
			<Bones>
				<Bone index="0" weight="255" />
				<Bone index="0" weight="0" />
				<Bone index="0" weight="0" />
				<Bone index="0" weight="0" />
			</Bones>
			<Normal x="0.3648316" y="-0.8986558" z="0.2435478" />
			<Texture x="0.6984127" y="0.01587301" />
		</Vertex>
		<Vertex>
			<Position x="-0.01814275" y="-0.09877682" z="0.141331" />
			<Bones>
				<Bone index="0" weight="255" />
				<Bone index="0" weight="0" />
				<Bone index="0" weight="0" />
				<Bone index="0" weight="0" />
			</Bones>
			<Normal x="0.4163995" y="-0.9061537" z="0.07414086" />
			<Texture x="0.6984127" y="0.4920635" />
		</Vertex>
		<Vertex>
			<Position x="0.05203632" y="-0.09717969" z="0.1077842" />
			<Bones>
				<Bone index="0" weight="255" />
				<Bone index="0" weight="0" />
				<Bone index="0" weight="0" />
				<Bone index="0" weight="0" />
			</Bones>
			<Normal x="0.430277" y="-0.9019167" z="0.03752234" />
			<Texture x="0.3968254" y="0.4920635" />
		</Vertex>
		<Vertex>
			<Position x="-0.03451334" y="-0.1518519" z="0.1473334" />
			<Bones>
				<Bone index="0" weight="255" />
				<Bone index="0" weight="0" />
				<Bone index="0" weight="0" />
				<Bone index="0" weight="0" />
			</Bones>
			<Normal x="0.4246749" y="-0.9050999" z="-0.02110521" />
			<Texture x="0.6984127" y="0.7301587" />
		</Vertex>
		<Vertex>
			<Position x="-0.01679905" y="-0.1947497" z="0.1383624" />
			<Bones>
				<Bone index="0" weight="255" />
				<Bone index="0" weight="0" />
				<Bone index="0" weight="0" />
				<Bone index="0" weight="0" />
			</Bones>
			<Normal x="0.3852754" y="-0.9200852" z="0.07075403" />
			<Texture x="0.6507937" y="0.8888889" />
		</Vertex>
	</Vertices>
	<View>
		<Indices>
			<Index>0</Index>
			<Index>1</Index>
			<Index>2</Index>
			<Index>3</Index>
			<Index>4</Index>
			<Index>5</Index>
			<Index>6</Index>
			<Index>7</Index>
			<Index>8</Index>
			<Index>9</Index>
			<Index>10</Index>
			<Index>11</Index>
			<Index>12</Index>
			<Index>13</Index>
			<Index>14</Index>
			<Index>15</Index>
			<Index>16</Index>
			<Index>17</Index>
			<Index>18</Index>
			<Index>19</Index>
			<Index>20</Index>
			<Index>21</Index>
			<Index>22</Index>
			<Index>23</Index>
			<Index>24</Index>
			<Index>25</Index>
			<Index>26</Index>
			<Index>27</Index>
			<Index>28</Index>
			<Index>29</Index>
			<Index>30</Index>
			<Index>31</Index>
			<Index>32</Index>
			<Index>33</Index>
			<Index>34</Index>
			<Index>35</Index>
			<Index>36</Index>
			<Index>37</Index>
			<Index>38</Index>
			<Index>39</Index>
			<Index>40</Index>
			<Index>41</Index>
			<Index>42</Index>
			<Index>43</Index>
			<Index>44</Index>
			<Index>45</Index>
			<Index>46</Index>
			<Index>47</Index>
			<Index>48</Index>
			<Index>49</Index>
			<Index>50</Index>
			<Index>51</Index>
			<Index>52</Index>
			<Index>53</Index>
			<Index>54</Index>
			<Index>55</Index>
			<Index>56</Index>
			<Index>57</Index>
			<Index>58</Index>
			<Index>59</Index>
			<Index>60</Index>
			<Index>61</Index>
			<Index>62</Index>
			<Index>63</Index>
			<Index>64</Index>
			<Index>65</Index>
			<Index>66</Index>
			<Index>67</Index>
			<Index>68</Index>
			<Index>69</Index>
			<Index>70</Index>
			<Index>71</Index>
			<Index>72</Index>
			<Index>73</Index>
			<Index>74</Index>
			<Index>75</Index>
			<Index>76</Index>
			<Index>77</Index>
			<Index>78</Index>
			<Index>79</Index>
			<Index>80</Index>
			<Index>81</Index>
			<Index>82</Index>
			<Index>83</Index>
			<Index>84</Index>
			<Index>85</Index>
			<Index>86</Index>
			<Index>87</Index>
			<Index>88</Index>
			<Index>89</Index>
			<Index>90</Index>
			<Index>91</Index>
			<Index>92</Index>
			<Index>93</Index>
			<Index>94</Index>
			<Index>95</Index>
			<Index>96</Index>
			<Index>97</Index>
			<Index>98</Index>
			<Index>99</Index>
			<Index>100</Index>
			<Index>101</Index>
			<Index>102</Index>
			<Index>103</Index>
			<Index>104</Index>
			<Index>105</Index>
			<Index>106</Index>
		</Indices>
		<Triangles>
			<Triangle>83</Triangle>
			<Triangle>84</Triangle>
			<Triangle>85</Triangle>
			<Triangle>84</Triangle>
			<Triangle>86</Triangle>
			<Triangle>85</Triangle>
			<Triangle>87</Triangle>
			<Triangle>85</Triangle>
			<Triangle>86</Triangle>
			<Triangle>87</Triangle>
			<Triangle>88</Triangle>
			<Triangle>85</Triangle>
			<Triangle>88</Triangle>
			<Triangle>89</Triangle>
			<Triangle>85</Triangle>
			<Triangle>89</Triangle>
			<Triangle>88</Triangle>
			<Triangle>90</Triangle>
			<Triangle>90</Triangle>
			<Triangle>88</Triangle>
			<Triangle>99</Triangle>
			<Triangle>90</Triangle>
			<Triangle>99</Triangle>
			<Triangle>98</Triangle>
			<Triangle>91</Triangle>
			<Triangle>90</Triangle>
			<Triangle>98</Triangle>
			<Triangle>91</Triangle>
			<Triangle>98</Triangle>
			<Triangle>97</Triangle>
			<Triangle>91</Triangle>
			<Triangle>97</Triangle>
			<Triangle>92</Triangle>
			<Triangle>91</Triangle>
			<Triangle>92</Triangle>
			<Triangle>93</Triangle>
			<Triangle>92</Triangle>
			<Triangle>94</Triangle>
			<Triangle>93</Triangle>
			<Triangle>92</Triangle>
			<Triangle>95</Triangle>
			<Triangle>94</Triangle>
			<Triangle>96</Triangle>
			<Triangle>95</Triangle>
			<Triangle>92</Triangle>
			<Triangle>96</Triangle>
			<Triangle>92</Triangle>
			<Triangle>97</Triangle>
			<Triangle>96</Triangle>
			<Triangle>97</Triangle>
			<Triangle>100</Triangle>
			<Triangle>96</Triangle>
			<Triangle>100</Triangle>
			<Triangle>101</Triangle>
			<Triangle>101</Triangle>
			<Triangle>100</Triangle>
			<Triangle>102</Triangle>
			<Triangle>101</Triangle>
			<Triangle>102</Triangle>
			<Triangle>103</Triangle>
			<Triangle>104</Triangle>
			<Triangle>101</Triangle>
			<Triangle>103</Triangle>
			<Triangle>103</Triangle>
			<Triangle>2</Triangle>
			<Triangle>104</Triangle>
			<Triangle>105</Triangle>
			<Triangle>2</Triangle>
			<Triangle>103</Triangle>
			<Triangle>105</Triangle>
			<Triangle>106</Triangle>
			<Triangle>2</Triangle>
			<Triangle>0</Triangle>
			<Triangle>2</Triangle>
			<Triangle>106</Triangle>
			<Triangle>0</Triangle>
			<Triangle>1</Triangle>
			<Triangle>2</Triangle>
			<Triangle>74</Triangle>
			<Triangle>73</Triangle>
			<Triangle>82</Triangle>
			<Triangle>73</Triangle>
			<Triangle>74</Triangle>
			<Triangle>75</Triangle>
			<Triangle>74</Triangle>
			<Triangle>76</Triangle>
			<Triangle>75</Triangle>
			<Triangle>74</Triangle>
			<Triangle>77</Triangle>
			<Triangle>76</Triangle>
			<Triangle>77</Triangle>
			<Triangle>78</Triangle>
			<Triangle>76</Triangle>
			<Triangle>78</Triangle>
			<Triangle>77</Triangle>
			<Triangle>79</Triangle>
			<Triangle>77</Triangle>
			<Triangle>80</Triangle>
			<Triangle>79</Triangle>
			<Triangle>74</Triangle>
			<Triangle>82</Triangle>
			<Triangle>81</Triangle>
			<Triangle>77</Triangle>
			<Triangle>74</Triangle>
			<Triangle>81</Triangle>
			<Triangle>77</Triangle>
			<Triangle>81</Triangle>
			<Triangle>80</Triangle>
			<Triangle>64</Triangle>
			<Triangle>63</Triangle>
			<Triangle>72</Triangle>
			<Triangle>63</Triangle>
			<Triangle>64</Triangle>
			<Triangle>65</Triangle>
			<Triangle>64</Triangle>
			<Triangle>66</Triangle>
			<Triangle>65</Triangle>
			<Triangle>64</Triangle>
			<Triangle>67</Triangle>
			<Triangle>66</Triangle>
			<Triangle>67</Triangle>
			<Triangle>68</Triangle>
			<Triangle>66</Triangle>
			<Triangle>68</Triangle>
			<Triangle>67</Triangle>
			<Triangle>69</Triangle>
			<Triangle>67</Triangle>
			<Triangle>70</Triangle>
			<Triangle>69</Triangle>
			<Triangle>64</Triangle>
			<Triangle>72</Triangle>
			<Triangle>71</Triangle>
			<Triangle>67</Triangle>
			<Triangle>64</Triangle>
			<Triangle>71</Triangle>
			<Triangle>67</Triangle>
			<Triangle>71</Triangle>
			<Triangle>70</Triangle>
			<Triangle>62</Triangle>
			<Triangle>55</Triangle>
			<Triangle>54</Triangle>
			<Triangle>53</Triangle>
			<Triangle>54</Triangle>
			<Triangle>55</Triangle>
			<Triangle>53</Triangle>
			<Triangle>56</Triangle>
			<Triangle>54</Triangle>
			<Triangle>56</Triangle>
			<Triangle>57</Triangle>
			<Triangle>54</Triangle>
			<Triangle>61</Triangle>
			<Triangle>54</Triangle>
			<Triangle>57</Triangle>
			<Triangle>61</Triangle>
			<Triangle>62</Triangle>
			<Triangle>54</Triangle>
			<Triangle>56</Triangle>
			<Triangle>58</Triangle>
			<Triangle>57</Triangle>
			<Triangle>59</Triangle>
			<Triangle>57</Triangle>
			<Triangle>58</Triangle>
			<Triangle>59</Triangle>
			<Triangle>60</Triangle>
			<Triangle>57</Triangle>
			<Triangle>60</Triangle>
			<Triangle>61</Triangle>
			<Triangle>57</Triangle>
			<Triangle>44</Triangle>
			<Triangle>43</Triangle>
			<Triangle>52</Triangle>
			<Triangle>43</Triangle>
			<Triangle>44</Triangle>
			<Triangle>45</Triangle>
			<Triangle>44</Triangle>
			<Triangle>46</Triangle>
			<Triangle>45</Triangle>
			<Triangle>44</Triangle>
			<Triangle>47</Triangle>
			<Triangle>46</Triangle>
			<Triangle>47</Triangle>
			<Triangle>48</Triangle>
			<Triangle>46</Triangle>
			<Triangle>48</Triangle>
			<Triangle>47</Triangle>
			<Triangle>49</Triangle>
			<Triangle>47</Triangle>
			<Triangle>50</Triangle>
			<Triangle>49</Triangle>
			<Triangle>44</Triangle>
			<Triangle>52</Triangle>
			<Triangle>51</Triangle>
			<Triangle>47</Triangle>
			<Triangle>44</Triangle>
			<Triangle>51</Triangle>
			<Triangle>47</Triangle>
			<Triangle>51</Triangle>
			<Triangle>50</Triangle>
			<Triangle>42</Triangle>
			<Triangle>35</Triangle>
			<Triangle>34</Triangle>
			<Triangle>33</Triangle>
			<Triangle>34</Triangle>
			<Triangle>35</Triangle>
			<Triangle>33</Triangle>
			<Triangle>36</Triangle>
			<Triangle>34</Triangle>
			<Triangle>36</Triangle>
			<Triangle>37</Triangle>
			<Triangle>34</Triangle>
			<Triangle>41</Triangle>
			<Triangle>34</Triangle>
			<Triangle>37</Triangle>
			<Triangle>41</Triangle>
			<Triangle>42</Triangle>
			<Triangle>34</Triangle>
			<Triangle>36</Triangle>
			<Triangle>38</Triangle>
			<Triangle>37</Triangle>
			<Triangle>39</Triangle>
			<Triangle>37</Triangle>
			<Triangle>38</Triangle>
			<Triangle>39</Triangle>
			<Triangle>40</Triangle>
			<Triangle>37</Triangle>
			<Triangle>40</Triangle>
			<Triangle>41</Triangle>
			<Triangle>37</Triangle>
			<Triangle>32</Triangle>
			<Triangle>25</Triangle>
			<Triangle>24</Triangle>
			<Triangle>23</Triangle>
			<Triangle>24</Triangle>
			<Triangle>25</Triangle>
			<Triangle>23</Triangle>
			<Triangle>26</Triangle>
			<Triangle>24</Triangle>
			<Triangle>26</Triangle>
			<Triangle>27</Triangle>
			<Triangle>24</Triangle>
			<Triangle>31</Triangle>
			<Triangle>24</Triangle>
			<Triangle>27</Triangle>
			<Triangle>31</Triangle>
			<Triangle>32</Triangle>
			<Triangle>24</Triangle>
			<Triangle>26</Triangle>
			<Triangle>28</Triangle>
			<Triangle>27</Triangle>
			<Triangle>29</Triangle>
			<Triangle>27</Triangle>
			<Triangle>28</Triangle>
			<Triangle>29</Triangle>
			<Triangle>30</Triangle>
			<Triangle>27</Triangle>
			<Triangle>30</Triangle>
			<Triangle>31</Triangle>
			<Triangle>27</Triangle>
			<Triangle>22</Triangle>
			<Triangle>15</Triangle>
			<Triangle>14</Triangle>
			<Triangle>13</Triangle>
			<Triangle>14</Triangle>
			<Triangle>15</Triangle>
			<Triangle>13</Triangle>
			<Triangle>16</Triangle>
			<Triangle>14</Triangle>
			<Triangle>16</Triangle>
			<Triangle>17</Triangle>
			<Triangle>14</Triangle>
			<Triangle>21</Triangle>
			<Triangle>14</Triangle>
			<Triangle>17</Triangle>
			<Triangle>21</Triangle>
			<Triangle>22</Triangle>
			<Triangle>14</Triangle>
			<Triangle>16</Triangle>
			<Triangle>18</Triangle>
			<Triangle>17</Triangle>
			<Triangle>19</Triangle>
			<Triangle>17</Triangle>
			<Triangle>18</Triangle>
			<Triangle>19</Triangle>
			<Triangle>20</Triangle>
			<Triangle>17</Triangle>
			<Triangle>20</Triangle>
			<Triangle>21</Triangle>
			<Triangle>17</Triangle>
			<Triangle>4</Triangle>
			<Triangle>3</Triangle>
			<Triangle>12</Triangle>
			<Triangle>3</Triangle>
			<Triangle>4</Triangle>
			<Triangle>5</Triangle>
			<Triangle>4</Triangle>
			<Triangle>6</Triangle>
			<Triangle>5</Triangle>
			<Triangle>4</Triangle>
			<Triangle>7</Triangle>
			<Triangle>6</Triangle>
			<Triangle>7</Triangle>
			<Triangle>8</Triangle>
			<Triangle>6</Triangle>
			<Triangle>8</Triangle>
			<Triangle>7</Triangle>
			<Triangle>9</Triangle>
			<Triangle>7</Triangle>
			<Triangle>10</Triangle>
			<Triangle>9</Triangle>
			<Triangle>4</Triangle>
			<Triangle>12</Triangle>
			<Triangle>11</Triangle>
			<Triangle>7</Triangle>
			<Triangle>4</Triangle>
			<Triangle>11</Triangle>
			<Triangle>7</Triangle>
			<Triangle>11</Triangle>
			<Triangle>10</Triangle>
		</Triangles>
		<Geosets>
			<Geoset triangle="0" triangles="318" />
		</Geosets>
		<Textures>
			<Texture geoset="0" color="-1" blend="0" layer="0" texture="0" transparency="0" />
		</Textures>
	</View>
	<Colors />
	<Textures>
		<Texture type="2" file="" />
	</Textures>
	<Transparencies>
		<Transparency>1</Transparency>
	</Transparencies>
	<Blending>
		<Blend>0</Blend>
	</Blending>
	<Attachments />
</Model>